{"version":"1.0","dataSet":{"info":{"date":"20230116","occupation":"ICT","channel":"MOCK","place":"ONLINE","gender":"MALE","ageRange":"55-","experience":"NEW"},"question":{"raw":{"text":"대학 생활을 하면서 가장 힘들었던 경험은 무엇이었습니까 그리고 그것을 어떻게 극복했는지도 함께 말씀해 주시기 바랍니다","wordCount":15},"emotion":[],"intent":[]},"answer":{"raw":{"text":"네 가장 어려웠던 점들은 다들 겪는 성적이라고 생각합니다. 제가 열심히 공부하고 노력했는데 어 성적은 조은케 나오지 않는 그런 경우가 가끔 있었기 때문에 그럴 때 많이 어려웠던 것 같습니다. 그리고 제가 공부하는 시간을 많이 잘 이용하지 못했던 그런 점도 조금 있는 것 같고 그래서 어 대학 생활이 여러 가지로 어려운 점이 많이 있었던 것 같습니다. 또 제 경제적인 능력도 조금 키워야 하고 그러다 보니까 어 공부하는 시간을 빼서 알바를 한다든가 다른 그런 업무에 많이 투입됐기 때문에 참 그런 점이 많이 어려웠던 것 같습니다. 하지만 어 최선을 다해서 열심히 대학 생활을 마쳤다고 생각하고 있기 때문에 그렇게 후회스럽지는 않습니다. 그 순간 순간간에 최선을 다하고 했지만 아 결과는 제가 바라던 만큼 나오지 않는 그런 상황도 있었기 때문에 하지만 그것이 다 제 어려움만은 아니고 누구나 다 겪는 사소한 어려움인 것 같아서 저는 뭐 크게 개의치 않고 있습니다. 하지만 지금 다시 대학 생활을 한다면 좀 더 알찬 어 계획을 세워서 그 계획대로 잘 추진해 나갈 것입니다. 그 당시에는 대학 생활에 대한 계획이나 어떤 목표가 정해놓고 뚜렷하게 하지 않은 것 같아서 그런 아쉬움이 저에게는 항상 남아 있고 앞으로 어떤 일을 하든지 계획을 철저하게 세워서 그에 맞게끔 추진해 나가야 된다고 생각하고 있습니다.","wordCount":184},"emotion":[],"intent":[{"text":"","expression":"","category":"attitude"}],"summary":{"text":"가장 어려웠던 점들은 다들 겪는 성적이라고 생각합니다. 제가 열심히 공부하고 노력했는데 성적이 잘 나오지 않는 경우가 종종 있었기 때문에 많이 어려웠던 것 같습니다. 하지만 최선을 다해서 대학 생활을 마무리했다고 생각하고 있기 때문에 그렇게 후회스럽지는 않습니다. 지금 다시 대학 생활을 한다면 좀 더 알찬 계획을 세워서 그 계획대로 잘 추진해 나갈 것입니다.","wordCount":51}}},"rawDataInfo":{"question":{"fileFormat":"wav","fileSize":426638,"duration":13330,"samplingBit":16,"channelCount":1,"samplingRate":"16kHz","audioPath":"/Mock/05.ICT/Male/New/ckmk_q_ict_m_n_409104.wav"},"answer":{"fileFormat":"wav","fileSize":3696718,"duration":115520,"samplingBit":16,"channelCount":1,"samplingRate":"16kHz","audioPath":"/Mock/05.ICT/Male/New/ckmk_a_ict_m_n_409104.wav"}}}