{"version":"1.0","dataSet":{"info":{"date":"20230116","occupation":"ICT","channel":"MOCK","place":"ONLINE","gender":"FEMALE","ageRange":"-34","experience":"NEW"},"question":{"raw":{"text":"지원자분께서 회사에 들어오시고 나서 선배님을 만나게 된다면 어떠한 모습의 선배를 만나고 싶으신지 궁금합니다 그렇게 하게 될 이유도 함께 말씀해 주시면 좋을 것 같습니다","wordCount":23},"emotion":[],"intent":[]},"answer":{"raw":{"text":"저는 회사에 들어와서 선배를 만나게 된다면 그런 선배를 만나고 싶습니다. 너무 이성적일 수 있는데요. 제가 열심히 하고 제가 잘하는 것들은 알아봐 주시면서 제가 못하는 부분들도 잘 알아주시지만 그것으로 책망하거나 채찍질보다는 왜 못하는지 어떻게 하면은 이 부분을 개선할 수 있는지 조언을 해 주시고 이끌어가 주실 수 있는 선배를 만나면 참 좋겠다 라는 로망은 있습니다. 제가 말씀드리고도 참 이상적인 것 같은데요. 만약에 제가 선배가 된다고 한다면 저는 그런 선배가 되고 싶습니다. 열심히 노력하는 후배의 모습을 알아봐주고 인정해주면서도 못하는 부분은 그럴 수 있다. 다독이면서 조언을 해주고 이끌어가 가는 그런 선배가 되고 싶다는 제 스스로의 로망도 있습니다. 그래서 저는 그런 선배를 만나게 된다고 한다면 아무리 힘들어도 이 선배 밑에서 만큼은 내가 정말 어떤 일이든 할 수 있을 것 같다. 이런 마음으로 회사에 임할 수 있고 또 그렇게 된다면 회사에서도 한 구성원으로서 더 좋은 실적을 낼 수 있고 더 큰 애사심으로 회사의 좋은 시너지 효과를 나타낼 수 있지 않을까 라는 생각을 해 봅니다. 그래서 저는 제가 회사에 들어간다면 앞서 말했듯 그런 선배를 만날 수 있으면 참 좋겠다. 그리고 내가 나중에 훗날 그런 선배가 돼야겠다 라고 생각합니다.","wordCount":171},"emotion":[],"intent":[{"text":"","expression":"","category":"attitude"}],"summary":{"text":"저는 열심히 하고 잘하는 것들은 알아봐 주시면서 어떻게 하면은 이 부분을 개선할 수 있는지 조언을 해 해주시고 이끌어가 주실 수 있는 선배를 만나고 싶습니다. 열심히 노력하는 후배의 모습을 알아봐주고 인정해주면서도 못하는 부분은 다독이면서 조언을 해주고 이끌어가 가는 그런 선배가 되고 싶다는 제 스스로의 로망도 있습니다.","wordCount":45}}},"rawDataInfo":{"question":{"fileFormat":"wav","fileSize":636878,"duration":19900,"samplingBit":16,"channelCount":1,"samplingRate":"16kHz","audioPath":"/Mock/05.ICT/Female/New/ckmk_q_ict_f_n_330575.wav"},"answer":{"fileFormat":"wav","fileSize":3871438,"duration":120980,"samplingBit":16,"channelCount":1,"samplingRate":"16kHz","audioPath":"/Mock/05.ICT/Female/New/ckmk_a_ict_f_n_330575.wav"}}}