{"version":"1.0","dataSet":{"info":{"date":"20230116","occupation":"ICT","channel":"MOCK","place":"ONLINE","gender":"MALE","ageRange":"55-","experience":"NEW"},"question":{"raw":{"text":"만약 상사가 회사의 이익에 반하는 행동을 하는 것을 본인이 직접 목격했다면 그때 어떻게 하시겠습니까","wordCount":14},"emotion":[],"intent":[]},"answer":{"raw":{"text":"아마 제가 선택을 하는 어떤 그 기반 기본이 되는 건 평소에 인제 같은 그 사무실에서 일을 하면서 어 뭐 서로가 인제 어느 정도는 성격이나 아니면 취향 그리고 어 언어의 화법 그리고 뭐 도덕성 뭐 이런 것까지 또 그리고 뭐 가정적이냐 아니면은 뭐 이 사회적 그 어떤 그런 부분까지도 어느 정도는 뭐 비밀스러운 일은 모르겠지만 어느 정도는 알고 있고 그 사람에 대한 나름의 어 안경은 끼고 있을 겁니다. 뭐 어 그래서 인제 그 상사가 회사의 이익에 반하는 행동을 할 때 아마 첫 번째 어 내가 평소에 어 존중하고 존경했던 상사이면은 어 어 저분이 왜 이런 행동을 할까 라는 어 그 사람의 입장에서 한번 생각을 해 보고 그리고 사실은 이제 직장은 음 우리 가족의 어 생활의 터전이지 않습니까. 그 터전을 어 훼손할 수는 없으니까 어 회사의 이익이 얼마나 손실이 날까 이런 이제 여러 가지 이제 복잡한 생각이 될 겁니다. 어 그런데 또 거부할 수는 없죠. 뭐 지금까지 인제 그 상사로부터 계속 지지 지시를 받아서 일을 수행하는 그런 입장이라면은 어 이미 어느 정도 사고는 어 많이 인제 어 어 습관화돼 있겠죠. 그래서 어 그것이 좀 많은 문제가 있을 것 같습니다.","wordCount":177},"emotion":[],"intent":[{"text":"","expression":"","category":"attitude"}],"summary":{"text":"상사가 회사의 이익에 반하는 행동을 할 때 그 상사의 입장에서 생각해 보고, 직장은 우리 가족의 생활의 터전인데 훼손할 수 없으니 회사 이익이 얼마나 손실이 날까 이런 복잡한 생각이 될 것입니다. 상사로부터 계속 지지 지시를 받아서 일을 수행하는 입장이라면 이미 사고는 많이 습관화돼 있으리라 생각됩니다.","wordCount":44}}},"rawDataInfo":{"question":{"fileFormat":"wav","fileSize":293198,"duration":9160,"samplingBit":16,"channelCount":1,"samplingRate":"16kHz","audioPath":"/Mock/05.ICT/Male/New/ckmk_q_ict_m_n_425696.wav"},"answer":{"fileFormat":"wav","fileSize":3857358,"duration":120540,"samplingBit":16,"channelCount":1,"samplingRate":"16kHz","audioPath":"/Mock/05.ICT/Male/New/ckmk_a_ict_m_n_425696.wav"}}}