{"version":"1.0","dataSet":{"info":{"date":"20230116","occupation":"ICT","channel":"MOCK","place":"ONLINE","gender":"FEMALE","ageRange":"35-44","experience":"NEW"},"question":{"raw":{"text":"만약 지금 본인이 내일 죽는다는 사실을 안다면 당장 무엇을 하시겠습니까 해당 면접을 끝까지 계속 보시겠습니까","wordCount":15},"emotion":[],"intent":[]},"answer":{"raw":{"text":"일단 제가 내일 죽는다는 사실을 제가 백 퍼센트 믿을 수 있느냐 없느냐에 따라서 어 지금 당장 해야 할 일이 어 바뀔 것 같습니다. 어 내일 제가 죽는다는 것을 어떻게 백 프로 어 신뢰할 수 있는지에 대한 의문이 먼저 듭니다. 어 그럴 경우에는 저는 어 이 면접도 끝까지 보면서 저의 일상을 어 변함없이 어 해 나갈 것입니다. 어제 했던 일 오늘 했던 일이 어 내일 죽는다고 해서 크게 달라지지 않고 저는 저의 소중한 일상을 평범하게 어 하루를 잘 마무리 할 것 같습니다. 그렇기 때문에 오늘 제가 이 면접을 보고 있다는 건 오늘 하루 저의 일과 중에 가장 중요한 일일 거라는 생각이 듭니다. 그렇기 때문에 이 중요한 일을 잘 마무리 어 하고 싶습니다. 어 그렇지만 만약에 내일 내가 죽는다는 사실이 백 퍼센트 어 신뢰할 수 있는 일이라면 저는 어 면접을 보는 대신 조용히 어 집으로 가서 저의 어 어떤 인생을 어 마무리하는 그런 작업들을 할 것 같습니다. 오랜 지인들에게 연락도 또 연락을 좀 하고 또 제가 살아온 인생에 대해 반추해 보면서 어 글을 적을 것 같습니다. 그래서 내가 어떤 삶을 살았는지 내가 내일 죽어도 어 물론 어 백 퍼센트 여한이 없는 것은 아니겠지만 어 제가 살아온 삶에 대해 감사하고 또한 제가 행복했던 순간들 그리고 내가 어 감사해야 될 사람들에 대한 어 그런 것들을 적어보면서 좀 정리를 하고 그런 좋은 기억을 가지고 어 삶을 어 마감하고 싶습니다.","wordCount":214},"emotion":[],"intent":[{"text":"","expression":"","category":"attitude"}],"summary":{"text":"오늘 했던 일이 내일 죽는다고 해서 크게 달라지지 않고 저의 소중한 일상을 평범하게 마무리 할 것 같습니다. 만약 내일 제가 죽는다는 사실이 백 퍼센트 신뢰할 수 있다면 면접을 보는 대신 조용히 집으로 가서 저의 삶을 마무리 할 것입니다. 제가 살아온 삶에 대해 감사하고 또 행복했던 순간들 그리고 감사해야 될 사람들에 대한 것들을 적어보면서 삶을 마감하고 싶습니다.","wordCount":56}}},"rawDataInfo":{"question":{"fileFormat":"wav","fileSize":316238,"duration":9880,"samplingBit":16,"channelCount":1,"samplingRate":"16kHz","audioPath":"/Mock/05.ICT/Female/New/ckmk_q_ict_f_n_404686.wav"},"answer":{"fileFormat":"wav","fileSize":3731598,"duration":116610,"samplingBit":16,"channelCount":1,"samplingRate":"16kHz","audioPath":"/Mock/05.ICT/Female/New/ckmk_a_ict_f_n_404686.wav"}}}