{"version":"1.0","dataSet":{"info":{"date":"20230116","occupation":"ICT","channel":"MOCK","place":"ONLINE","gender":"FEMALE","ageRange":"-34","experience":"NEW"},"question":{"raw":{"text":"얼마 전에 구급대원이 주취자에게 폭행을 당해서 순직 당하는 일이 있었습니다 지원자님은 해당 사건에 대해서 어떻게 생각하시나요","wordCount":16},"emotion":[],"intent":[]},"answer":{"raw":{"text":"얼마 전 구급 대원이 주취자에게 폭행을 당해 순직하는 당하는 일이 있었습니다. 언뜻 보면 주취자가 나쁜 사람인 것 같지만 저는 그때 당시 현장에 있었고 구급 대원이 주치자에게 먼저 폭행을 유도한 장면을 저는 보았습니다. 하지만 언론에서는 구급 대원이라 하면 긍정적인 단어를 대표하고 주취자는 부정적인 단어를 대표한다고 느끼기에 주취자에 의해 구급 대원이 순직 당한 것처럼 포장이 된 게 아닌가 라는 생각이 듭니다. 주취자이지만 겉으로 봤을 때는 멀쩡히 일상을 보낼 수 있는 모습이었기 때문에 너무 한쪽으로 치우쳐진 언론 플레이가 아닌가 라는 생각을 조심스럽게 해 봅니다. 순직 당하신 부분에 대해서는 저도 많이 안타까운 마음을 갖고 있지만 서로 조심하고 서로 배려하고 서로 조금 더 참고 양보하면서 살아간다면 어땠을까 라는 생각을 해 봅니다.","wordCount":106},"emotion":[],"intent":[{"text":"","expression":"","category":"attitude"}],"summary":{"text":"최근 구급 대원이 주취자에게 폭행을 당해 순직하는 일이 있었습니다. 언뜻 주취자가 나쁜 사람인 것 같지만, 사실은 긍정적인 단어를 대표한다고 느껴서 너무 한쪽으로 치우친 것 같습니다. 순직 당하신 부분에 대해서는 저도 많이 안타까운 마음입니다.","wordCount":33}}},"rawDataInfo":{"question":{"fileFormat":"wav","fileSize":628558,"duration":19640,"samplingBit":16,"channelCount":1,"samplingRate":"16kHz","audioPath":"/Mock/05.ICT/Female/New/ckmk_q_ict_f_n_296149.wav"},"answer":{"fileFormat":"wav","fileSize":3644238,"duration":113880,"samplingBit":16,"channelCount":1,"samplingRate":"16kHz","audioPath":"/Mock/05.ICT/Female/New/ckmk_a_ict_f_n_296149.wav"}}}