{"version":"1.0","dataSet":{"info":{"date":"20230116","occupation":"ICT","channel":"MOCK","place":"ONLINE","gender":"MALE","ageRange":"-34","experience":"NEW"},"question":{"raw":{"text":"입사 후 근무를 하면서 면접자님이 생각하시는 분야와 잘 맞지 않는다는 사실을 깨닫게 된다면 어떻게 대처하시겠습니까","wordCount":15},"emotion":[],"intent":[]},"answer":{"raw":{"text":"입사 후 근무를 하면서 지원한 부서가 잘 맞지 않는다면 즉 제가 생각했던 것들과 많이 달랐다면 어떤 것들이 달랐는지 제가 이 질문을 준비하면서 알게 되었던 업무들과 실무에서 어떤 부분들의 차이가 있었고 이것이 다른 회사들에게도 해당되는 것인지를 먼저 확인해 볼 것입니다. 만약 다른 회사들도 마찬가지로 해당 직무가 똑같은 업무 프로세스로 이루어져 있다는 것을 알게 된다면 우선 최대한 잘 할 수 있을 때까지 노력을 해 보고 그렇게 한 후에도 맞지 않는다는 것을 알게 된다면 제가 가고 싶은 다른 직무를 잘 찾아보면서 생각을 해 볼 것이고 결정을 해서 부서 이동을 신청 드릴 것 같습니다. 맞지 않는 업무를 계속해서 하고 있는다면 같이 일을 하고 있는 동료들에게도 좋지 않을 것이고 저에게도 좋지 않을 것이라고 생각하기 때문입니다.","wordCount":110},"emotion":[],"intent":[{"text":"","expression":"","category":"attitude"}],"summary":{"text":"입사 후 지원한 부서가 잘 맞지 않는다면 업무와 실무에서의 차이가 다른 회사들에게도 해당되는 것인지 확인해 볼 것입니다. 맞지 않는 업무를 계속해서 하고 있다면 같이 일하는 동료들에게도 좋지 않을 것이라고 생각하기 때문입니다.","wordCount":31}}},"rawDataInfo":{"question":{"fileFormat":"wav","fileSize":391118,"duration":12220,"samplingBit":16,"channelCount":1,"samplingRate":"16kHz","audioPath":"/Mock/05.ICT/Male/New/ckmk_q_ict_m_n_444984.wav"},"answer":{"fileFormat":"wav","fileSize":2701518,"duration":84420,"samplingBit":16,"channelCount":1,"samplingRate":"16kHz","audioPath":"/Mock/05.ICT/Male/New/ckmk_a_ict_m_n_444984.wav"}}}