{"version":"1.0","dataSet":{"info":{"date":"20230116","occupation":"ICT","channel":"MOCK","place":"ONLINE","gender":"FEMALE","ageRange":"-34","experience":"NEW"},"question":{"raw":{"text":"지원자분은 이전 회사에서 현재 지원한 개발과 다른 분야인 직무에 근무한 걸로 알고 있습니다 지원자 분은 왜 전 회사를 그만두고 개발을 하러 오셨을까요","wordCount":22},"emotion":[],"intent":[]},"answer":{"raw":{"text":"전에 다니던 회사에서는 비전도 좋았고 가치관도 저와 부합했고 너무 열심히 하고 싶었는데 회사 자금이 생각보다 많이 부족했고 어느 정도 시점이 지나고 나니까 월급이 들어오지 않았습니다. 그래도 저는 그 회사에 대한 비전과 꿈을 믿고 있었고 저의 미래를 거기서 일궈 나가고 싶었기 때문에 몇 개월 동안 월급이 꾸준히 밀리는데도 불구하고 끝까지 저는 열심히 일했습니다. 그러다 어느 날 제게 월급이 계속 밀리는 것이 미안하니 재택 근무를 해라 라고 제안을 해 주셨습니다. 갈수록 상황이 안 좋아지는 것을 몸소 느끼고 체험하다 보니 안타깝게도 이직을 결정할 수 밖에 없었습니다. 지금 제가 회 제 제가 지금 지원한 이 회사 또 제가 꾸고 있는 꿈과 비전이 굉장히 부합하다고 생각을 합니다. 뿐만 아니라 회사 자본이 안정적이고 업계 계열 십 순위 안에 들고 있다는 점을 알기에 안정감을 갖고 최선을 다해 일하고 싶습니다.","wordCount":122},"emotion":[],"intent":[{"text":"","expression":"","category":"attitude"}],"summary":{"text":"저는 전에 일하던 회사에서는 자금이 부족했지만 비전을 믿고 열심히 일했습니다. 그러던 중 어느 날 재택 근무를 제안해 주셨습니다. 상황을 체험하다 보니 이직을 결정할 수 밖에 없었습니다. 지금 제가 지원한 이 회사와 제가 꾸고 있는 꿈과 비전에 부합하니 안정감을 갖고 최선을 다해 일하고 싶습니다.","wordCount":43}}},"rawDataInfo":{"question":{"fileFormat":"wav","fileSize":449358,"duration":14040,"samplingBit":16,"channelCount":1,"samplingRate":"16kHz","audioPath":"/Mock/05.ICT/Female/New/ckmk_q_ict_f_n_303090.wav"},"answer":{"fileFormat":"wav","fileSize":3856718,"duration":120520,"samplingBit":16,"channelCount":1,"samplingRate":"16kHz","audioPath":"/Mock/05.ICT/Female/New/ckmk_a_ict_f_n_303090.wav"}}}