{"version":"1.0","dataSet":{"info":{"date":"20230116","occupation":"ICT","channel":"MOCK","place":"ONLINE","gender":"MALE","ageRange":"55-","experience":"NEW"},"question":{"raw":{"text":"지원자님께서는 자신의 십 년 후 미래는 어떨 것 같으신가요 혹시 저희 회사에 계속 다니고 계실 것 같으신가요","wordCount":17},"emotion":[],"intent":[]},"answer":{"raw":{"text":"네 제 생각에는 계속 다닐 수 있다고 생각합니다. 왜냐하면 제가 선택한 일이고 또는 저에게 잘 맞는 일이라는 판단도 있기 때문에 그렇게 생각합니다. 어떤 분야에서 일을 할 때에는 그 일에 지속적인 업무가 수행돼야 좋은 결과도 항상 창출할 수 있고 또 더 발전을 할 수 있다고 생각합니다. 물론 회사가 어 지속적으로 다닐 수 없는 환경에 처해질 수도 있습니다. 그럴 때는 어쩔 수 없다고 하겠습니다. 하지만 그렇지 않은 경우는 저는 계속 다닐 수 있다고 생각합니다. 왜냐하면 그렇게 함으로써 제 생활에 리듬을 계속 유지할 수 있고 또는 어 제 능력을 어느 정도 인정받을 수 있는 그런 자리에 갈 수도 있기 때문에 현재 한 곳에서 오랫동안 근무하는 것을 저는 어 많이 좋은 이미지를 갖고 있습니다. 그래서 저는 자주 어 이직을 하거나 이런 것은 별로 도움이 안 된다고 생각합니다. 물론 이직함으로써 더 좋은 자리 더 좋은 대우를 받을 수도 있습니다. 하지만 그렇게 할 때는 순간적인 생각이 들 수도 있고 또는 후회하는 일이 생길 수도 있습니다. 항상 이직이나 어떤 행위를 할 때는 심사숙고해야 된다고 생각합니다. 그렇지만 저는 어떤 일을 시작하면 그 일에서 계속 어 일을 진행하고 또 하고 싶습니다. 그렇게 함으로써 내 발전이 더욱더 잘 될 수 있다고 생각하고 저도 또 회사에 좋은 음 성과를 내서 이익을 창출하는 데 일조하는 그런 자세가 될 수 있기 때문에 저는 어 계속해서 이 회사에 근무할 수 있다고 생각합니다.","wordCount":208},"emotion":[],"intent":[{"text":"","expression":"","category":"attitude"}],"summary":{"text":"어떤 분야에서 일을 할 때는 그 일에 지속적인 업무가 수행돼야 좋은 결과도 항상 창출하고 또 더 발전을 할 수 있다고 생각합니다. 이직이나 어떤 행위를 할 때는 심사숙고해야 되지만, 저는 어떤 일을 시작하면 그 일에서 계속 일을 하고 싶습니다. 그렇게 함으로써 내 발전이 더욱더 잘 될 수 있고 나도 또 회사에 좋은 음 성과를 내서 이익을 창출하는 데 일조하는 자세가 될 수 있기 때문에 저는 계속해서 이 회사에 근무할 수 있습니다.","wordCount":70}}},"rawDataInfo":{"question":{"fileFormat":"wav","fileSize":375118,"duration":11720,"samplingBit":16,"channelCount":1,"samplingRate":"16kHz","audioPath":"/Mock/05.ICT/Male/New/ckmk_q_ict_m_n_402150.wav"},"answer":{"fileFormat":"wav","fileSize":3754958,"duration":117340,"samplingBit":16,"channelCount":1,"samplingRate":"16kHz","audioPath":"/Mock/05.ICT/Male/New/ckmk_a_ict_m_n_402150.wav"}}}