{"version":"1.0","dataSet":{"info":{"date":"20230116","occupation":"ICT","channel":"MOCK","place":"ONLINE","gender":"FEMALE","ageRange":"35-44","experience":"NEW"},"question":{"raw":{"text":"본인의 장단점을 말씀해 주세요 그리고 그것들을 각각 특화 시키고 극복하기 위해 어떤 노력들을 했는지 그 부분도 같이 설명해 주세요","wordCount":19},"emotion":[],"intent":[]},"answer":{"raw":{"text":"저는 평소에도 진지한 면을 가지고 있어서 농담도 진담으로 알아듣곤 합니다. 그래서 주변에서 딱딱하다 는 소리를 많이 듣게 되었는데 이를 극복하고 유머러스한 성격을 가지기 위해 노력했습니다. 우선 재미있는 유머 책들을 읽고 재미있는 인터넷 동영상을 보고 티비에서 개그 프로그램을 시청했습니다. 그렇게 해서 제가 마음의 여유를 가지고 그것들을 따라 하면서 주변 사람들을 웃기려고 노력했습니다. 처음에는 딱딱하고 심심했던 모습이었지만 이제는 개그스럽고 재치있다 는 모습으로 바뀌어서 유쾌한 성격으로 거듭난 것 같습니다.","wordCount":66},"emotion":[{"text":"처음에는 딱딱하고 심심했던 모습이었지만 이제는 개그스럽고 재치있다 는 모습으로 바뀌어서 유쾌한 성격으로 거듭난 것 같습니다.","expression":"p-achievement","category":"positive"}],"intent":[{"text":"처음에는 딱딱하고 심심했던 모습이었지만 이제는 개그스럽고 재치있다 는 모습으로 바뀌어서 유쾌한 성격으로 거듭난 것 같습니다.","expression":"c_person","category":"background"}],"summary":{"text":"저는 원래 딱딱한 성격인데, 유머러스한 성격을 가지기 위해 노력하면서 딱딱하고 심심했던 모습이 개그스럽고 재치있다 는 모습으로 바뀌어서 유쾌한 성격으로 거듭난 것 같습니다.","wordCount":22}}},"rawDataInfo":{"question":{"fileFormat":"wav","fileSize":327758,"duration":10240,"samplingBit":16,"channelCount":1,"samplingRate":"16kHz","audioPath":"/Mock/05.ICT/Female/New/ckmk_q_ict_f_n_321748.wav"},"answer":{"fileFormat":"wav","fileSize":1860558,"duration":58140,"samplingBit":16,"channelCount":1,"samplingRate":"16kHz","audioPath":"/Mock/05.ICT/Female/New/ckmk_a_ict_f_n_321748.wav"}}}