{"version":"1.0","dataSet":{"info":{"date":"20230116","occupation":"ICT","channel":"MOCK","place":"ONLINE","gender":"MALE","ageRange":"-34","experience":"NEW"},"question":{"raw":{"text":"일을 하다 보면 영어로 서류를 작성해야 할 수도 있는데요 지원자님은 이런 영어 서류 작성에 어려움 없이 진행하실 수 있나요","wordCount":19},"emotion":[],"intent":[]},"answer":{"raw":{"text":"네 영어로 서류를 작성해야 한다면 현재로써는 영어로 서류를 작성하는 게 굉장히 힘든 일이지만 앞으로는 영어로 서류를 작성해 보고 싶습니다. 아마도 네 중요한 부분일 텐데요. 서류를 작성해보고 상사분에게 허락을 맞는다던지 아니면 등등의 방식을 통해서 영어로 서류를 작성하는 것은 굉장히 즐겁게 와 닿았습니다. 오늘도 컴업 이십 이라는 컨퍼런스를 다녀왔는데 그 안에서 영어로 공부해서 영어로 발표를 해 주시는 분도 계셨고 아마 국회의원 분인가 기억은 안 나는데 영어를 잘 못 하시는데 노력하시는 모습이 너무 멋졌습니다. 그리고 네 어른들이 떨지만 그렇게 시도하는 모습이 너무나도 멋있었고 저도 영어로 서류를 작성하는 것을 그러한 방식을 통해서 진행해 보고 싶었습니다. 감사합니다. 노력해 봐야죠.","wordCount":94},"emotion":[{"text":"서류를 작성해보고 상사분에게 허락을 맞는다던지 아니면 등등의 방식을 통해서 영어로 서류를 작성하는 것은 굉장히 즐겁게 와 닿았습니다.","expression":"p-interest","category":"positive"},{"text":"그리고 네 어른들이 떨지만 그렇게 시도하는 모습이 너무나도 멋있었고 저도 영어로 서류를 작성하는 것을 그러한 방식을 통해서 진행해 보고 싶었습니다.","expression":"p-interest","category":"positive"}],"intent":[{"text":"","expression":"","category":"attitude"}],"summary":{"text":"영어로 서류를 작성하는 것은 굉장히 힘들지만 앞으로 시도해 보고 싶습니다. 상사분에게 허락을 받는다던지 아니면 등의 방식을 통해서 영어로 서류 작성은 굉장히 즐거웠습니다. 컴업20 이라는 컨퍼런스에서 영어로 발표해 주시는 분의 모습이 멋졌습니다.","wordCount":31}}},"rawDataInfo":{"question":{"fileFormat":"wav","fileSize":581838,"duration":18180,"samplingBit":16,"channelCount":1,"samplingRate":"16kHz","audioPath":"/Mock/05.ICT/Male/New/ckmk_q_ict_m_n_312152.wav"},"answer":{"fileFormat":"wav","fileSize":2711438,"duration":84730,"samplingBit":16,"channelCount":1,"samplingRate":"16kHz","audioPath":"/Mock/05.ICT/Male/New/ckmk_a_ict_m_n_312152.wav"}}}