{"version":"1.0","dataSet":{"info":{"date":"20230116","occupation":"ICT","channel":"MOCK","place":"ONLINE","gender":"MALE","ageRange":"-34","experience":"NEW"},"question":{"raw":{"text":"소프트웨어 개발 중에 문제가 발생했을 수 있습니다 혹시 발생했을 때 본인만의 해결책이나 어 해결 방안이 있으면 자세하게 얘기해 주십시오","wordCount":19},"emotion":[],"intent":[]},"answer":{"raw":{"text":"소프트웨어를 개발하면서 문제가 발생하면 먼저 기능이 다른 작업자와 기능이 맞물려 있는 경우에 빠르게 이러한 사실을 전달하는 것이 중요하고 그 다음에 원인을 빠르게 찾아서 해결하는 것이 중요하다고 생각했습니다. 우선 기능이 맞물려 있는 경우에 다른 작업자가 구현하고 있는 기능 또한 영향이 있을 가능성이 있고 실제로 그러할 경우에는 전체적으로 코드를 고쳐야 할 수 있기 때문에 이를 알리는 것이 중요하다고 생각하였습니다. 그리고 나서 원인을 빠르게 파악해야 하는 데 이전에 이미 작성해 놓은 부분을 이어서 구현하고 있었던 경우에는 우선 그 이후에 작성된 부분에 대해서 문제가 발생한 코드를 출력해 보며 찾아보고 찾고 나서 해결을 하면 되고 이전에 코드가 잘못되었을 경우에는 이전 코드까지 모두 수정하여 문제를 해결해야 된다고 생각합니다.","wordCount":102},"emotion":[],"intent":[{"text":"","expression":"","category":"attitude"}],"summary":{"text":"소프트웨어를 개발하면서 문제가 발생하면 다른 작업자와 기능이 맞물려 있는 경우 빨리 이런 사실을 전달해야 하고, 그 다음에 원인을 빨리 찾아 해결하는 것이 중요하다고 생각했습니다.","wordCount":24}}},"rawDataInfo":{"question":{"fileFormat":"wav","fileSize":496718,"duration":15520,"samplingBit":16,"channelCount":1,"samplingRate":"16kHz","audioPath":"/Mock/05.ICT/Male/New/ckmk_q_ict_m_n_473426.wav"},"answer":{"fileFormat":"wav","fileSize":2689358,"duration":84040,"samplingBit":16,"channelCount":1,"samplingRate":"16kHz","audioPath":"/Mock/05.ICT/Male/New/ckmk_a_ict_m_n_473426.wav"}}}