{"version":"1.0","dataSet":{"info":{"date":"20230116","occupation":"ICT","channel":"MOCK","place":"ONLINE","gender":"MALE","ageRange":"45-54","experience":"NEW"},"question":{"raw":{"text":"자신의 의견을 주장할 때 강하게 주장하는 편이신가요 아니면 어떤 스타일로 자신의 의견을 주장하시는지 말씀해 주세요","wordCount":15},"emotion":[],"intent":[]},"answer":{"raw":{"text":"네 제가 제 주장을 어 할 때는 어 확실한 음 근거나 팩트가 있고 또 어 어떤 그 뒤집을 수 없는 사실이라면 강하게 주장을 하는 편입니다. 왜냐하면 어 이거 분명한 사실이고 또 뭐 뒤집어지고 또 번복될 만한 어 내용이 아니기 때문에 이 사실을 정확하게 전달해서 어 다른 음 오류에 빠지 빠지지 않고 또 실수를 하지 않도록 하기 위해서 어 강하게 주장하는 경우가 있습니다. 하지만 어 어떤 사실이나 팩트를 근거로 하는 주장이 아니라 어떤 예상을 하는 부분이나 어떤 제 의견을 단지 얘기할 때는 강하게 주장하지는 않는 것 같습니다. 음 그래서 미래를 미래를 미래에 대한 어떤 예측을 할 때 어 근거와 사실에 관한 얘기는 어 그것이 어떤 잘 그 회의에서 구성원들 간에 잘 믿지를 못하고 어 어 착각을 일으킨다면 팩트를 가지고는 절대로 물러서지 않고 강력하게 제 주장을 내세웁니다. 그래야지 다른 피해가 생기지 않기 때문입니다. 이상입니다.","wordCount":132},"emotion":[],"intent":[{"text":"","expression":"","category":"attitude"}],"summary":{"text":"저는 확실한 근거나 사실이 있고 뒤집을 수 없는 사실이라면 강하게 주장을 하는 편이지만, 어떤 예상을 하는 부분이나 제 의견을 단지 말할 때는 강하게 주장하지 않는 것 같습니다. 즉 미래를 예측할 때 근거와 사실에 관한 얘기를 구성원들 간에 잘 믿지 못하고 착각을 하게 된다면 강력하게 제 주장을 내세웠습니다.","wordCount":47}}},"rawDataInfo":{"question":{"fileFormat":"wav","fileSize":396238,"duration":12380,"samplingBit":16,"channelCount":1,"samplingRate":"16kHz","audioPath":"/Mock/05.ICT/Male/New/ckmk_q_ict_m_n_381875.wav"},"answer":{"fileFormat":"wav","fileSize":3553358,"duration":111040,"samplingBit":16,"channelCount":1,"samplingRate":"16kHz","audioPath":"/Mock/05.ICT/Male/New/ckmk_a_ict_m_n_381875.wav"}}}