{"version":"1.0","dataSet":{"info":{"date":"20230116","occupation":"ICT","channel":"MOCK","place":"ONLINE","gender":"MALE","ageRange":"35-44","experience":"EXPERIENCED"},"question":{"raw":{"text":"만약 본인이 상사가 회사의 이익에 반하는 행동을 하는 것을 직접 목격한다면 그때 어떻게 행동하시겠습니까","wordCount":14},"emotion":[],"intent":[]},"answer":{"raw":{"text":"아 이게 굉장히 어려운 문제인 것 같은데요. 그 상사가 회사의 이익에 반하는 행동이라는 것을 제가 스스로 판단하는 것 자체가 큰 어 큰 문제가 있다고 봅니다. 상사는 어 저보다 물론은 어 사회생활이나 그리고 현재 다니는 이 직장에서 저보다는 더 많이 근무를 했 했을 것이고 이 회사에 대해서 더 이해도가 높을 거라고 저는 믿고 있고요. 그 상사가 아 회사의 이익에 반하는 행동을 했을지언정 그것이 어떤 이유가 있을 거라고 저는 그 상사를 우선 믿어 볼 믿어 보겠습니다. 제가 그것을 뭐 막기 위해서 어 뭐 대들어서 뭐 이렇게 그걸 제재할 수 있는 것도 아니고 그렇게 한다고 해서 어 어떻게 쉽게 해결될 문제가 아니라는 것을 알고 있기 때문에 일단 저의 의견은 조심스럽게 말씀드릴 수는 있겠지만 어 그 상사에 그 모든 행동에는 어떠한 뜻이 있을 거라고 어 우선적으로는 생각할 것입니다.","wordCount":124},"emotion":[],"intent":[{"text":"","expression":"","category":"attitude"}],"summary":{"text":"상사가 회사의 이익에 반하는 행동을 했다고 스스로 판단하는 것 자체가 큰 문제가 있습니다. 상사가 저보다 더 많은 근무를 했고 회사에 대해 더 이해도가 높을 것입니다. 그 상사를 믿어 보겠습니다. 그 행동에 어떤 뜻이 있을 것이고 우선적으로는 생각할 것입니다.","wordCount":38}}},"rawDataInfo":{"question":{"fileFormat":"wav","fileSize":375118,"duration":11720,"samplingBit":16,"channelCount":1,"samplingRate":"16kHz","audioPath":"/Mock/05.ICT/Male/Experienced/ckmk_q_ict_m_e_258287.wav"},"answer":{"fileFormat":"wav","fileSize":2247438,"duration":70230,"samplingBit":16,"channelCount":1,"samplingRate":"16kHz","audioPath":"/Mock/05.ICT/Male/Experienced/ckmk_a_ict_m_e_258287.wav"}}}