{"version":"1.0","dataSet":{"info":{"date":"20230116","occupation":"ICT","channel":"MOCK","place":"ONLINE","gender":"FEMALE","ageRange":"-34","experience":"NEW"},"question":{"raw":{"text":"면접자께서 일하면서 가장 어려울 것으로 예상되는 건 어떤 것이 있나요 그리고 그 어려움을 어떻게 대처하실 것인지 설명 부탁드리겠습니다","wordCount":18},"emotion":[],"intent":[]},"answer":{"raw":{"text":"아무래도 비 개발자 인력 음 동료분들과의 커뮤니케이션에 있어서 가장 어려울 것으로 생각됩니다. 예전에 어 컴공 외에 타학과 분들과 좀 협업해서 공모전을 진행했던 적이 있는데 어 그 당시 저는 개발 부문 쪽에 몸담고 있었고 프론트 어 프론트 쪽을 이제 담당하고 있었는데 어 타 전공에 이 기획을 맡은 분들은 어 개발의 언어와 어떤 생태를 잘 모르다 보니까 자신들이 요구하는 것에 어떤 업무 강도나 어 아니면은 그 작업 용어 이런 부분들에 있어서 서로 좀 상충하는 부분들이 있었습니다. 네 그래서 이러한 부분들을 어 다음번 공모전에 교훈을 삼아서 어느 정도 숙달하고 있는 그런 분들과 또 대화를 나누고 공모전을 진행했었는데 어 이런 식으로 제 경험이 있는 분들과의 어떤 협업을 진행한다면 어 더욱 더 수월한 개발 작업이 있을 것이고 만약 그럴 수 없다면 제가 개발에 관한 어 기본적인 부분들을 알려주구 어 커뮤니케이션에 관한 가이드를 드릴 것 같습니다.","wordCount":130},"emotion":[],"intent":[{"text":"","expression":"","category":"attitude"}],"summary":{"text":"저는 개발 부문에 몸담고 있었고 프론트 쪽을 담당하고 있었는데 타 전공에 근무하시는 분들은 개발 언어와 생태에 대해 잘 모르셔서 업무 강도나 작업 용어 등에서 상충하는 부분이 있었습니다. 경험있는 분들과의 협업을 진행한다면 더욱 수월한 개발 작업이 있을 것이고 커뮤니케이션에 관한 가이드를 줄 것 같습니다.","wordCount":43}}},"rawDataInfo":{"question":{"fileFormat":"wav","fileSize":452558,"duration":14140,"samplingBit":16,"channelCount":1,"samplingRate":"16kHz","audioPath":"/Mock/05.ICT/Female/New/ckmk_q_ict_f_n_67626.wav"},"answer":{"fileFormat":"wav","fileSize":2879758,"duration":89990,"samplingBit":16,"channelCount":1,"samplingRate":"16kHz","audioPath":"/Mock/05.ICT/Female/New/ckmk_a_ict_f_n_67626.wav"}}}