{"version":"1.0","dataSet":{"info":{"date":"20230116","occupation":"ICT","channel":"MOCK","place":"ONLINE","gender":"MALE","ageRange":"55-","experience":"NEW"},"question":{"raw":{"text":"본인이 직접 해외 출장 장소를 선택할 수 있다면 꼭 한 번 가서 일을 해보고 싶은 곳이 있을 텐데요 그 나라가 어디인지 저희에게 설명 부탁드리겠습니다","wordCount":24},"emotion":[],"intent":[]},"answer":{"raw":{"text":"네 출장을 간다면 저는 싱가포르를 한 번 가보고 싶습니다. 싱가포르는 우선 사회 간접 자본과 또 사람들이 생활하는 시스템이 잘 갖춰져 있다고 보고 있습니다. 그리고 그 좁은 나라에서도 많은 관광객들이 찾아오는 이유를 한 번 느껴보고 싶기도 하고요. 또 우리나라 못지않는 아이티 기술도 발달돼 있다고 들 알고 있습니다. 그래서 우리나라와 어떤 차이점이 있고 어떤 점에서 이렇게 발전할 수 있었나도 한번 비교해 보고 싶습니다. 그래서 어 싱가폴이라는 나라로 출장을 한 번 갔으면 하는 그런 바램이 있습니다. 그렇게 해서 도시의 환경 깨끗함 그 나라의 의식 수준 등 다양한 것을 어 접해보고 싶습니다. 그렇게 함으로써 저 또한 우리나라에 돌아왔을 때 저 자신을 돌아볼 수 있고 주변 사람들에게 어떤 어 이야기를 해줄 수 있고 도움도 줄 수 있다는 그런 어 판단이 되고 있습니다. 그래서 저는 싱가포르에 대한 기대가 조금 있습니다. 어떻게 해서 이렇게 사회 안전망을 잘 간추렸고 사람들의 불만을 을 잠재우면서 성장할 수 있었을까 하는 그런 것도 엿볼 수 있지 않을까 싶습니다. 우리나라도 해서 보면 잘 발달되는 것으로 판단할 수 있습니다. 하지만 우리나라는 불만이 많은 사회가 팽배해지고 있습니다. 그래서 저는 그거와 비유해 보고 싶고 또 일이 업무도 물론 잘 해야 되지만 국민성에 대한 기대를 한 번 가져보고 싶습니다.","wordCount":182},"emotion":[],"intent":[{"text":"","expression":"","category":"attitude"}],"summary":{"text":"싱가포르에 출장을 가보고 싶습니다. 사회 간접 자본과 사람들이 생활하는 시스템이 잘 갖춰져 있고, 우리나라 못지않는 아이티 기술도 발달돼 있다고 들 알고 있습니다. 그래서 싱가폴이라는 나라로 출장을 한번 갔다면 도시의 환경 깨끗함 그 나라의 의식 수준 등 다양한 것을 접해본 후 우리나라에 돌아왔을 때 자신을 돌아볼 수 있고 주변 사람들에게 어떤 이야기를 해줄 수 있고 도움을 줄 수 있을 것이라고 생각합니다.","wordCount":60}}},"rawDataInfo":{"question":{"fileFormat":"wav","fileSize":377678,"duration":11800,"samplingBit":16,"channelCount":1,"samplingRate":"16kHz","audioPath":"/Mock/05.ICT/Male/New/ckmk_q_ict_m_n_402091.wav"},"answer":{"fileFormat":"wav","fileSize":3749838,"duration":117180,"samplingBit":16,"channelCount":1,"samplingRate":"16kHz","audioPath":"/Mock/05.ICT/Male/New/ckmk_a_ict_m_n_402091.wav"}}}