{"version":"1.0","dataSet":{"info":{"date":"20230116","occupation":"ICT","channel":"MOCK","place":"ONLINE","gender":"MALE","ageRange":"55-","experience":"NEW"},"question":{"raw":{"text":"본인이 창의적으로 어떤 문제를 해결한 경험이 있으신가요 해결 과정에 대해서 자세하게 말씀해 주시기 바랍니다","wordCount":14},"emotion":[],"intent":[]},"answer":{"raw":{"text":"창의적으로 문제를 해결한 경우가 있습니다. 싱가폴에서 실험적인 화상회의 시스템을 도입하는 것이었는데 한국에서 했던 것처럼 프로젝이 잘 진행되지 않았습니다. 원인을 조사한 결과 싱가폴에서 사용하고 있는 기술은 한국 기술과 약간 다른 점이 있었습니다. 그거를 규정 자체를 바꾸는 것은 시간적으로나 물리적으로나 불가능한 상황이었고 그들의 정보통신부를 접촉하여 일시적인 임시적인 소통을 위한 체제를 만들어 달라고 요청했습니다. 다행히도 그 요청은 받아들여졌고 프로젝트를 성공리에 마칠 수 있었습니다.","wordCount":60},"emotion":[],"intent":[{"text":"","expression":"","category":"attitude"}],"summary":{"text":"창의적으로 문제를 해결한 경우가 있습니다. 싱가폴에서 실험적인 화상회의 시스템을 도입하는 것이었는데, 규정 변경이 불가능했고 그들의 정보통신부를 접촉하여 일시적인 임시적인 소통을 위한 체제를 요청했습니다.","wordCount":23}}},"rawDataInfo":{"question":{"fileFormat":"wav","fileSize":570958,"duration":17840,"samplingBit":16,"channelCount":1,"samplingRate":"16kHz","audioPath":"/Mock/05.ICT/Male/New/ckmk_q_ict_m_n_341743.wav"},"answer":{"fileFormat":"wav","fileSize":2236238,"duration":69880,"samplingBit":16,"channelCount":1,"samplingRate":"16kHz","audioPath":"/Mock/05.ICT/Male/New/ckmk_a_ict_m_n_341743.wav"}}}