{"version":"1.0","dataSet":{"info":{"date":"20230116","occupation":"ICT","channel":"MOCK","place":"ONLINE","gender":"MALE","ageRange":"55-","experience":"NEW"},"question":{"raw":{"text":"만약 지원자님께서 게임 속의 캐릭터라면 어떤 게임에서 어떤 역할을 맡아서 수행하고 싶으십니까","wordCount":12},"emotion":[],"intent":[]},"answer":{"raw":{"text":"예 저는 많은 사람들에게 희망을 줄 수 있고 또 어떤 도움을 줄 수 있는 그런 어 게임 속의 캐릭터가 저는 하고 싶습니다. 예를 들어 어려운 사람이 어려운 난처한 일을 당했을 때 그것을 해결해 줄 수 있고 도와줄 수 있는 그런 캐릭터 또는 어 제가 어떤 일을 행함으로써 많은 사람들에게 도움이 줄 수 있는 그런 캐릭터가 저는 하고 싶습니다. 어떤 게임 속에서나 항상 도움이 되는 그런 캐릭터가 저는 제에게 잘 맞는다고 생각합니다. 그래서 어 어떤 환경이나 작업 또는 위치에 있다 하더라도 항상 도움이 되는 그런 사람이 되고 싶습니다. 또 게임 속에서도 그런 캐릭터가 있다면 그것을 하고 싶은 어 꿈이 있습니다. 왜냐하면은 남을 돕는 일이나 제가 선행을 베풀었을 때 항상 저에게 더 많은 어 기쁨과 행복이 이루어지기 때문에 그렇습니다. 어 살아보는 생활에서는 남에게 해를 주면 내 자신도 해롭습니다. 남에게 행복을 주면 저 자신도 즐겁습니다. 그렇기 때문에 게임 속에서라도 저는 남에게 즐거움과 행복을 줄 수 있는 그런 캐릭터가 있다면 그것을 맡아서 해보고 싶은 그런 생각을 가지고 있습니다. 모든 일을 함에 있어서 남에게 즐거움과 동시에 불행을 줄 수 있습니다만 저는 즐거움을 주는 쪽으로 더 많은 비중을 주는 그런 캐릭터가 좋은 것 같습니다.","wordCount":178},"emotion":[],"intent":[{"text":"","expression":"","category":"attitude"}],"summary":{"text":"많은 사람들에게 희망과 어떤 도움을 줄 수 있는 게임 속의 캐릭터가 저는 좋습니다. 어떤 환경이나 작업 또는 위치에 있다 하더라도 항상 도움이 되는 사람이 되고 싶습니다. 또 게임 속에서도 그런 캐릭터가 있다면 그것을 하고 싶은 꿈이 있습니다. 모든 일에 있어 타인에게 즐거움과 불행을 줄 수 있지만 저는 즐거움을 주는 쪽으로 비중을 주는 캐릭터가 좋다고 생각합니다.","wordCount":55}}},"rawDataInfo":{"question":{"fileFormat":"wav","fileSize":294478,"duration":9200,"samplingBit":16,"channelCount":1,"samplingRate":"16kHz","audioPath":"/Mock/05.ICT/Male/New/ckmk_q_ict_m_n_401538.wav"},"answer":{"fileFormat":"wav","fileSize":3815118,"duration":119220,"samplingBit":16,"channelCount":1,"samplingRate":"16kHz","audioPath":"/Mock/05.ICT/Male/New/ckmk_a_ict_m_n_401538.wav"}}}