{"version":"1.0","dataSet":{"info":{"date":"20230116","occupation":"ICT","channel":"MOCK","place":"ONLINE","gender":"FEMALE","ageRange":"-34","experience":"NEW"},"question":{"raw":{"text":"지원자님께서는 휴식을 취할 때 주로 어떤 일들을 하십니까 그리고 왜 그 일을 하는지 이유도 함께 말씀해 주시기 바랍니다","wordCount":18},"emotion":[],"intent":[]},"answer":{"raw":{"text":"어 제가 휴식을 취할 때는요. 우선 핸드폰을 정말 많이 하죠. 거의 일상의 대부분이 그거일 정도로 자랑은 아니지만 핸드폰으로 쫌 할 게 많아요. 콘텐츠들도 유투브 콘텐츠들도 굉장히 많이 보고 또 이제 그걸로도 만화나 드라마나 영화도 볼 수 있어 가지고 최대한 보는 편입니다. 요즘은 쫌 덜 보고 있지만 그래도 그런 걸 많이 하구요. 뭔가를 많이 봐요. 보는 것을 통해서 이제 또 배우는 게 많기 때문에 많은 것을 보려고 노력하고 이제 게임도 굉장히 많이 하죠. 게임을 굉장히 좋아하는데 어 요즘 리듬 게임이랑 뭐 이것저것 연애 시뮬레이션도 해 가지고 또 뭐 액션 게임등등 서바이벌 이런 저런 거를 많이 하죠. 그런 식으로 이제 휴식을 취하는 편이고 뭔가 좀 해야겠다 싶을 때는 이제 작품 하나 제가 자료를 자료를 만들어서 이제 그거를 녹음을 해서 유튜브에 올리고 그런 식으로 이제 휴식을 취하는 편입니다.","wordCount":125},"emotion":[],"intent":[{"text":"","expression":"","category":"attitude"}],"summary":{"text":"휴식을 취할 때는 핸드폰으로 할 게 많고 유투브 콘텐츠들도 많이 보고 만화나 드라마나 영화도 최대한 봅니다. 게임을 굉장히 좋아하는데 리듬 게임이나 연애 시뮬레이션, 액션 게임, 서바이벌 같은 게임을 많이 합니다. 작품 하나 자료를 만들어 녹음을 해서 유튜브에 올리고 휴식을 취합니다.","wordCount":40}}},"rawDataInfo":{"question":{"fileFormat":"wav","fileSize":419918,"duration":13120,"samplingBit":16,"channelCount":1,"samplingRate":"16kHz","audioPath":"/Mock/05.ICT/Female/New/ckmk_q_ict_f_n_436713.wav"},"answer":{"fileFormat":"wav","fileSize":3154318,"duration":98570,"samplingBit":16,"channelCount":1,"samplingRate":"16kHz","audioPath":"/Mock/05.ICT/Female/New/ckmk_a_ict_f_n_436713.wav"}}}