{"version":"1.0","dataSet":{"info":{"date":"20230116","occupation":"ICT","channel":"MOCK","place":"ONLINE","gender":"MALE","ageRange":"-34","experience":"NEW"},"question":{"raw":{"text":"지금까지 살아오면서 가장 힘들었던 경험은 무엇입니까 그것을 어떻게 극복하셨는지도 궁금합니다","wordCount":10},"emotion":[],"intent":[]},"answer":{"raw":{"text":"네 제가 가장 힘들었던 경험은 주로 마음이 아플 때가 가장 힘든 것 같습니다. 이것은 모두가 마찬가지일 것 같은데요. 어떻게 보면 몸이 무너지는 것도 물리적으로 해결하기 쉽지 않겠지만 마음이 무너진 상태가 오래 가면 거기에서부터 체력적으로 쌓아 올리는 것은 더욱 힘들더라구요. 그게 쉽지가 않았습니다. 마음이 무너지면 몸을 쌓아올릴 법한 정신적 체력이 없습니다. 몸적 체력도 마찬가지구요. 그런 근본적인 것이 없는 것이 어떻게 보면 돈이 좀 없거나 일이 좀 안 풀리거나 다양한 그 프라 피라미드의 위엣 단에 있는 성과들은 그 아랫단으로부터 이어져 오는 것 같고 그래서 기반적인 곳으로 역할을 하는 마음 건강 그 위에 몸 건강 이러한 것들이 잘 탄탄해 탄탄하게 있지 않다면 네 좋지 않은 결론들을 마주치는 것 같습니다. 제가 극복했던 경험도 이것을 해결함으로써 극복했었습니다.","wordCount":112},"emotion":[],"intent":[{"text":"","expression":"","category":"attitude"}],"summary":{"text":"마음 건강 그 위에 몸 건강이 탄탄하게 있지 않으면 좋지 않은 결론들을 마주치는 것 같습니다. 제가 극복했던 경험도 이것을 해결함으로써 극복했었습니다.","wordCount":21}}},"rawDataInfo":{"question":{"fileFormat":"wav","fileSize":326798,"duration":10210,"samplingBit":16,"channelCount":1,"samplingRate":"16kHz","audioPath":"/Mock/05.ICT/Male/New/ckmk_q_ict_m_n_328816.wav"},"answer":{"fileFormat":"wav","fileSize":2757198,"duration":86160,"samplingBit":16,"channelCount":1,"samplingRate":"16kHz","audioPath":"/Mock/05.ICT/Male/New/ckmk_a_ict_m_n_328816.wav"}}}