{"version":"1.0","dataSet":{"info":{"date":"20230116","occupation":"ICT","channel":"MOCK","place":"ONLINE","gender":"FEMALE","ageRange":"-34","experience":"NEW"},"question":{"raw":{"text":"지원자가 인지하고 계시는 정보 보안에 관련된 이슈를 한 가지 언급하고 언급하신 이슈에 관한 지원자의 생각을 말씀해 주세요","wordCount":17},"emotion":[],"intent":[]},"answer":{"raw":{"text":"정보 보안 관련돼서 알고 있는 이슈 한 가지를 언급해 보자면 예전에 그런 말이 많이 돌았었습니다. 갤럭시는 한국인이 사용하기는 편리하지만 보안이 약하다 아이폰은 한국인이 사용하기 편리하지는 않지만 보안이 강하다 이런 이야기가 정말 많이 돌았었는데요. 마침 그때 당시 갤럭시 유저들의 핸드폰이 해킹이 되면서 많은 연예인들의 폰이 해킹이 되면서 그 안에 있는 사생활을 담은 사진들이 유출이 됐던 적이 있습니다. 그리고 그 사진들이 유출이 되고 또 대화 내용이 유출이 되면서 그 사람들의 이미지가 금이 가며 팬들의 신뢰를 잃어버리는 그런 안타까운 상황이 있었던 것을 기억합니다. 저는 많은 사람들이 우스갯소리로 안드로이드 체제는 조금 보완이 약해 아이오에스 체제는 보완이 강해 이렇게 말들 하고 넘기지만 그 말이 저는 맞다고 생각을 합니다. 핸드폰은 아주 개인적인 물품이기 때문에 특히나 높은 사람이고 또 유명세를 타고 일을 하는 사람들 같은 경우에는 더더욱 더 잘 지켜져야 한다고 생각합니다. 그래서 안드로이드 체제의 정보 보안 강화를 더욱 힘써야 되지 않나 라고 조심스럽게 저의 생각을 말씀드려 봅니다.","wordCount":141},"emotion":[],"intent":[{"text":"갤럭시는 한국인이 사용하기는 편리하지만 보안이 약하다","expression":"i_secty","category":"attitude"},{"text":"아이폰은 한국인이 사용하기 편리하지는 않지만 보안이 강하다","expression":"i_secty","category":"attitude"},{"text":"저는 많은 사람들이 우스갯소리로 안드로이드 체제는 조금 보완이 약해 아이오에스 체제는 보완이 강해 이렇게 말들 하고 넘기지만 그 말이 저는 맞다고 생각을 합니다.","expression":"i_secty","category":"attitude"},{"text":"핸드폰은 아주 개인적인 물품이기 때문에 특히나 높은 사람이고 또 유명세를 타고 일을 하는 사람들 같은 경우에는 더더욱 더 잘 지켜져야 한다고 생각합니다.","expression":"i_secty","category":"attitude"},{"text":"그래서 안드로이드 체제의 정보 보안 강화를 더욱 힘써야 되지 않나 라고 조심스럽게 저의 생각을 말씀드려 봅니다.","expression":"i_secty","category":"attitude"}],"summary":{"text":"연예인의 휴대폰이 해킹을 거치면서 사생활이 담긴 사진들과 대화 내용이 유출이 되고 그 사람들의 이미지에 금이 가서 팬들의 신뢰를 잃어버리는 안타까운 상황이 있었습니다. 그래서 안드로이드 체제의 정보 보안 강화를 더욱 힘써야 되지 않을까 생각합니다.","wordCount":33}}},"rawDataInfo":{"question":{"fileFormat":"wav","fileSize":361358,"duration":11290,"samplingBit":16,"channelCount":1,"samplingRate":"16kHz","audioPath":"/Mock/05.ICT/Female/New/ckmk_q_ict_f_n_347824.wav"},"answer":{"fileFormat":"wav","fileSize":3723598,"duration":116360,"samplingBit":16,"channelCount":1,"samplingRate":"16kHz","audioPath":"/Mock/05.ICT/Female/New/ckmk_a_ict_f_n_347824.wav"}}}