{"version":"1.0","dataSet":{"info":{"date":"20230116","occupation":"ICT","channel":"MOCK","place":"ONLINE","gender":"MALE","ageRange":"45-54","experience":"NEW"},"question":{"raw":{"text":"네이버 다음 구글의 검색을 비교해 보시고 각각 검색 엔진들의 차이점과 장단점에 대해서 설명해 주시기 바랍니다","wordCount":15},"emotion":[],"intent":[]},"answer":{"raw":{"text":"네이버와 다음의 경우에는 우리나라 토종 검색 엔진이라고 봐야 되겠지요. 네이버와 다음은 검색 엔진에 해당한다기 보다는 포털 성격의 서비스가 더 강하다고 생각을 합니다. 포털은 많은 류의 정보 서비스를 수평적으로 포괄적으로 보여주는 성격이 강하기 때문에 내가 원하는 정보를 맞춤형으로 찾아내기에는 좀 부족하다는 생각이 들 때가 많습니다. 이에 반해서 구글의 검색 엔진은 말 그대로 정보 서비스 검색의 최적화된 검색 엔진으로 보여집니다. 내가 원하는 어떤 정보를 찾고자 할 때 나에게 맞는 정보가 제공되는 경우가 네이버나 다음에 비해서 구글로 검색했을 때 더 많은 정보가 검색되는 것을 피부로 느끼게 됩니다. 그래서 구글은 참으로 맞춤형 검색 엔진이 아닌가 생각이 되구요. 네이버의 같은 경우는 주로 지식 서비스나 카페 서비스를 저는 많이 사용하는 편이고 다음 같은 경우는 블로그 서비스를 주로 많이 사용하는 편입니다.","wordCount":114},"emotion":[],"intent":[{"text":"","expression":"","category":"attitude"}],"summary":{"text":"네이버와 다음과 달리 구글은 정보 서비스 검색의 최적화된 검색 엔진으로 보여집니다. 원하는 정보를 찾고자 할 때 자신에게 맞는 정보가 제공되는 경우가 네이버나 다음에 비해서 구글로 검색했을 때 더 많은 정보가 검색되는 것을 피부로 느끼게 됩니다.","wordCount":35}}},"rawDataInfo":{"question":{"fileFormat":"wav","fileSize":593678,"duration":18550,"samplingBit":16,"channelCount":1,"samplingRate":"16kHz","audioPath":"/Mock/05.ICT/Male/New/ckmk_q_ict_m_n_360969.wav"},"answer":{"fileFormat":"wav","fileSize":2935758,"duration":91740,"samplingBit":16,"channelCount":1,"samplingRate":"16kHz","audioPath":"/Mock/05.ICT/Male/New/ckmk_a_ict_m_n_360969.wav"}}}