{"version":"1.0","dataSet":{"info":{"date":"20230116","occupation":"ICT","channel":"MOCK","place":"ONLINE","gender":"MALE","ageRange":"55-","experience":"NEW"},"question":{"raw":{"text":"그동안 속해 계셨던 조직과 단체 속에서 본인은 주로 어떤 역할을 하는 사람이었습니까","wordCount":12},"emotion":[],"intent":[]},"answer":{"raw":{"text":"어 저는 뭐 젊은 시절에 아버지가 인제 뭐 창업을 하신 그 제조업의 일을 하면서 뭐 그 폐업 신고도 내가 했으니까 사실은 어 그 인제 작은 제조업이지만 어 어느 정도 성장을 하기까지 아 많은 이제 피와 땀을 어 흘렸죠. 그러면서 인제 뭐 그 사람 관리나 뭐 자금 관리나 어 물량 관리나 뭐 모든 부분을 제가 총괄를 했습니다. 음 그랬으니까 뭐 어 리더십이 있는 뭐 그런 어 역량은 있고요. 어 그리고 어 목조 주택 팀장으로서 뭐 최근에는 어 모 인제 그 목조 주택 회사의 어 어 팀장으로 어 일을 했습니다. 뭐 한 삼 년 정도 일을 했는데 어 제가 팀을 어 구축해 가지고 어 회사가 계약한 건축주의 집을 어 골조부터 해 가지고 마감까지 에 공정 관리를 하고 또 기능적으로도 또 인제 어 직접 일을 하고 하는 그런 인제 역할을 했고 그리고 인제 공사 관계된 공정을 관리하기 때문에 뭐 설비나 전기 여러 인제 공정들이 어 관리를 해야 되니까 뭐 현장 소장 역할이 되는 거죠. 또 그 건축주가 뭐 어 오기도 하고 하니까 어 외부 사람에 대한 또 인제 그 담당을 해야 되는 역할이라서 현장 소장 역할도 뭐 겸하고 그런 역할로 이제 쭉 어 온 것 같습니다.","wordCount":183},"emotion":[],"intent":[{"text":"","expression":"","category":"attitude"}],"summary":{"text":"작은 제조업이지만 성장을 하기까지 많은 피와 땀을 흘렸죠. 그러면서 모든 부분을 제가 총괄했습니다. 그리고 목조 주택 회사의 팀장으로 일을 했습니다. 팀을 구축해 가지고 계약한 건축주의 집을 골조부터 마감까지 공정 관리를 하고 기능적으로도 직접 일을 하고, 설비나 전기 공정들이 관리를 해야 되니까 현장 소장 역할입니다.","wordCount":44}}},"rawDataInfo":{"question":{"fileFormat":"wav","fileSize":241678,"duration":7550,"samplingBit":16,"channelCount":1,"samplingRate":"16kHz","audioPath":"/Mock/05.ICT/Male/New/ckmk_q_ict_m_n_426996.wav"},"answer":{"fileFormat":"wav","fileSize":3625998,"duration":113310,"samplingBit":16,"channelCount":1,"samplingRate":"16kHz","audioPath":"/Mock/05.ICT/Male/New/ckmk_a_ict_m_n_426996.wav"}}}