{"version":"1.0","dataSet":{"info":{"date":"20230116","occupation":"ICT","channel":"MOCK","place":"ONLINE","gender":"MALE","ageRange":"55-","experience":"NEW"},"question":{"raw":{"text":"지원자님은 평소에 개인 작업을 많이 하는 편이신가요 그렇다면 그렇게 꾸준히 할 수 있는 원동력은 무엇이라고 생각하십니까","wordCount":16},"emotion":[],"intent":[]},"answer":{"raw":{"text":"지금은 이제 뭐 늦가을이라서 어 제가 뽑아야 될 풀들이 없는데 어 봄부터 시작하면은 뭐 시간 나는 대로 평소에 어 마당에 에 풀을 많이 뽑는 편입니다. 그리고 어 뭐 그 규모는 한 삼백 한 사십 평 명 정도 되죠. 어 여기에 삼 년 뒤에는 어 뭔가 인제 작품이 될 만한 그런 아름다움 어 목조 주택을 어 짓고 싶어서 그런 목표를 해서 인제 땅을 다지고 있는 거죠. 지금 현재로는 뭐 건축비가 없어 가지고 시간이 필요합니다. 스텝 바이 스텝으로 어 건축을 하게 되는데 어 그 건축물은 음 우리 부부의 뭐 삶에 그릇이기도 하지만 어 우리 손주들의 고향이 될 수 있는 그런 공간을 마련해 줄려고 생각하니까 뭔가 좀 음 계속 움직일 수 있는 그런 이제 원동력이 되고 또 인제 어 어 목표가 그렇게 어 생기는 거죠. 어 그래서 그 집은 진짜 제가 어 지금까지 이 지은 집 중에는 가장 어 작품성이 있는 어 집을 지을 겁니다. 어 그리고 그 다음 한 삼 년 뒤에는 한 이십 평대에 이제 한 동을 지어서 어 그거는 펜션 용도로 어 어 활용할 생각입니다.","wordCount":165},"emotion":[],"intent":[{"text":"","expression":"","category":"attitude"}],"summary":{"text":"지금 건축비가 없어 가지고 스텝 바이 스텝으로 건축을 하게 되는데 그 건축물은 우리 부부의 삶에 그릇이기도 하지만 우리 손주들의 고향이 될 수 있는 공간을 마련해 줄려고 생각하니까 계속 움직일 수 있는 원동력이 되고 또 목표가 생기는 겁니다. 그 다음 한 삼 년 뒤에는 한 20 평대에 한 동을 지어서 펜션 용도로 활용할 계획입니다.","wordCount":53}}},"rawDataInfo":{"question":{"fileFormat":"wav","fileSize":410318,"duration":12820,"samplingBit":16,"channelCount":1,"samplingRate":"16kHz","audioPath":"/Mock/05.ICT/Male/New/ckmk_q_ict_m_n_396725.wav"},"answer":{"fileFormat":"wav","fileSize":3283278,"duration":102600,"samplingBit":16,"channelCount":1,"samplingRate":"16kHz","audioPath":"/Mock/05.ICT/Male/New/ckmk_a_ict_m_n_396725.wav"}}}