{"version":"1.0","dataSet":{"info":{"date":"20230116","occupation":"ICT","channel":"MOCK","place":"ONLINE","gender":"FEMALE","ageRange":"-34","experience":"NEW"},"question":{"raw":{"text":"사내 스터디를 만들어 공부할 수 있다면 어떤 것을 공부하고 싶으신가요 공부하고 싶으신 그 이유도 함께 말씀 부탁드리겠습니다","wordCount":17},"emotion":[],"intent":[]},"answer":{"raw":{"text":"사내 스터디를 만들어 공부할 수 있다면 저는 일본어 스터디를 만들고 싶습니다. 귀사가 일본 회사와 밀접한 관련이 있고 일본과 아주 일을 많이 하기 때문에 일본어가 필수라고 생각합니다. 저 또한 일본어를 할 수 있기 때문에 다른 사람들에게 큰 도움을 줄 수 있을 것이라고 생각하기 때문입니다. 스터디를 할 때 여러 가지 요인들이 필요한데요. 첫 번째로는 목표를 확실히 해야 할 것입니다. 스터디를 하는 이유는 다양하겠지만 시험을 대비한다거나 혹은 회화를 위해서 라거나 다양한 이유가 있겠지만 제가 사내 스터디를 만드는 이유는 조금 더 회사의 업무에 원활하게 적용시키기 위해서입니다. 그렇기 때문에 제가 생각하는 목표는 회사의 업무를 조금 더 원활하게 할 수 있는 이 시스템을 만들기 위해서입니다. 세 번째로는 친목 도모를 위한 스터디는 피할 것입니다. 스터디를 하다 보면 친해지는 부분이 있는데 이게 너무 친목 도모 쪽으로 쏠리게 되면 자연스럽게 술자리도 늘어나고 이러다 보면 공부를 위한 목적이 흐려지는 것 같습니다. 그렇기 때문에 최대한 스터디의 목적에 맞게 행동을 할 것입니다. 또한 마지막으로 지각이나 숙제에 대한 규칙을 정해서 공부를 할 것입니다. 스터디가 저 뿐만이 아니라 팀원들에 대해서도 규칙이 있으면 조금 더 각 잡고 공부를 할 수 있을 것이라고 생각을 합니다. 제 답변은 이러합니다. 감사합니다.","wordCount":173},"emotion":[],"intent":[{"text":"","expression":"","category":"attitude"}],"summary":{"text":"사내 스터디를 만들어 일본어를 할 수 있다면 좋겠습니다. 회사 업무에 원활하게 적용시키기 위해 목표를 확실히 해야 하고, 친목 도모를 위한 스터디는 피할 것입니다. 지각이나 숙제에 대한 규칙을 정해서 공부를 할 것입니다.","wordCount":31}}},"rawDataInfo":{"question":{"fileFormat":"wav","fileSize":334158,"duration":10440,"samplingBit":16,"channelCount":1,"samplingRate":"16kHz","audioPath":"/Mock/05.ICT/Female/New/ckmk_q_ict_f_n_404865.wav"},"answer":{"fileFormat":"wav","fileSize":3838158,"duration":119940,"samplingBit":16,"channelCount":1,"samplingRate":"16kHz","audioPath":"/Mock/05.ICT/Female/New/ckmk_a_ict_f_n_404865.wav"}}}