{"version":"1.0","dataSet":{"info":{"date":"20230116","occupation":"ICT","channel":"MOCK","place":"ONLINE","gender":"MALE","ageRange":"-34","experience":"NEW"},"question":{"raw":{"text":"자신의 전공 이외에 수준급의 실력이 될 정도로 노력한 것이 따로 있으신가요 있다면 전공과 관련해서 어떤 도움을 주었는지도 궁금합니다","wordCount":18},"emotion":[],"intent":[]},"answer":{"raw":{"text":"네 저는 실제 전기 전자를 전공하였지만 이외에도 업무상 필요하였기에 컴퓨터 관련 전공 관련 지식도 노력을 하였습니다. 특히나 최근 유튜브에 공개된 대학 학부 강의가 많은데 이 중 스탠포드의 씨에스 이 삼 일 엔 컴퓨터 비전 강의를 학습하였고 이를 통해 컴퓨터 비전 지식을 쌓았습니다. 해당 전공 관련 지식은 저에게 머신러닝 딥러닝에 입문하는 계기가 되었고 현재 훌륭하게 엠 에이 티 엘 직무에서 업무를 수행하고 있습니다.","wordCount":62},"emotion":[],"intent":[{"text":"특히나 최근 유튜브에 공개된 대학 학부 강의가 많은데 이 중 스탠포드의 씨에스 이 삼 일 엔 컴퓨터 비전 강의를 학습하였고 이를 통해 컴퓨터 비전 지식을 쌓았습니다.","expression":"i_hwsw_prfi","category":"attitude"},{"text":"해당 전공 관련 지식은 저에게 머신러닝 딥러닝에 입문하는 계기가 되었고 현재 훌륭하게 엠 에이 티 엘 직무에서 업무를 수행하고 있습니다.","expression":"i_hwsw_prfi","category":"attitude"}],"summary":{"text":"업무상 필요로 컴퓨터 관련 전공 지식을 쌓아 머신러닝 딥러닝에 입문하였고 현재 훌륭하게 엠 에이 티 엘 직무에서 업무를 수행하고 있습니다.","wordCount":20}}},"rawDataInfo":{"question":{"fileFormat":"wav","fileSize":481358,"duration":15040,"samplingBit":16,"channelCount":1,"samplingRate":"16kHz","audioPath":"/Mock/05.ICT/Male/New/ckmk_q_ict_m_n_405532.wav"},"answer":{"fileFormat":"wav","fileSize":1614798,"duration":50460,"samplingBit":16,"channelCount":1,"samplingRate":"16kHz","audioPath":"/Mock/05.ICT/Male/New/ckmk_a_ict_m_n_405532.wav"}}}