{"version":"1.0","dataSet":{"info":{"date":"20230116","occupation":"ICT","channel":"MOCK","place":"ONLINE","gender":"FEMALE","ageRange":"55-","experience":"NEW"},"question":{"raw":{"text":"개발 프로세스에서 어떤 게 제일 재미있었나요","wordCount":6},"emotion":[],"intent":[]},"answer":{"raw":{"text":"네 아주 작은 그 피씨 에서 우체국에서 처음에 오에이 를 개발할 때 어 우체국 오에이 그 개발 프로그램을 짜본 적이 있습니다. 그 과정 중에 저는 아주 작은 출력에 관련된 어 프로젝트를 저는 했었습니다. 아주 큰 프로젝트 중에서도 저는 작은 부분이긴 했지만 예 그때는 아주 젊은 시절에 어 밤도 새 가면서 또 코드를 맞춰 가면서 어 또 어 그 업무 우체국 업무의 다양한 출력 양식이 있다는 것도 굉장히 재미있게 생각을 했었었구요. 또 제가 어떤 그 트렌드의 내지는 어 큰 그 우정사업본부라고 하죠. 그 우정사업본부라고 해주는 그 어 에서 에서 관할에서 운영하고 있는 프로젝트의 제가 일단 어 젊은 나이에 참석할 수 있고 일원이 될 수 있다는 부분이 굉장히 저는 어 재미있었습니다. 또 재미뿐만 아니라 어떤 책임감도 느꼈었구요. 그다음에 코드 하나 하나를 어 이렇게 맞춰가는 것들이 굉장히 재미있었고 하나는 또 제일 좋은 그 경험 중의 하나는 결과가 굉장히 깔끔하게 나왔던 거 제가 만든 결과가 굉장히 깔끔하게 칭찬을 받은 부분들이 저한테는 굉장히 재미있던 이유로 어 생각이 납니다.","wordCount":153},"emotion":[{"text":"그 우정사업본부라고 해주는 그 어 에서 에서 관할에서 운영하고 있는 프로젝트의 제가 일단 어 젊은 나이에 참석할 수 있고 일원이 될 수 있다는 부분이 굉장히 저는 어 재미있었습니다.","expression":"p-happiness","category":"positive"}],"intent":[{"text":"","expression":"","category":"attitude"}],"summary":{"text":"우체국 오에이 개발 과정 중에 작은 출력에 관련된 프로젝트를 했습니다. 젊은 시절에 코드 맞춰가면서 업무 우체국 업무의 다양한 출력 양식을 생각했고, 젊은 나이에 참석할 수 있고 일원이 될 수 있다는 부분이 재미있었습니다. 또 책임감도 느꼈고, 코드 하나를 맞춰가는 것이 재미있었고 좋은 경험 중의 하나는 결과가 정확하게 나왔던 것입니다.","wordCount":48}}},"rawDataInfo":{"question":{"fileFormat":"wav","fileSize":239758,"duration":7490,"samplingBit":16,"channelCount":1,"samplingRate":"16kHz","audioPath":"/Mock/05.ICT/Female/New/ckmk_q_ict_f_n_362955.wav"},"answer":{"fileFormat":"wav","fileSize":3037518,"duration":94920,"samplingBit":16,"channelCount":1,"samplingRate":"16kHz","audioPath":"/Mock/05.ICT/Female/New/ckmk_a_ict_f_n_362955.wav"}}}