{"version":"1.0","dataSet":{"info":{"date":"20230116","occupation":"ICT","channel":"MOCK","place":"ONLINE","gender":"FEMALE","ageRange":"-34","experience":"NEW"},"question":{"raw":{"text":"이제까지 진행한 프로젝트들 중에서 제일 기억에 남는 프로젝트가 있다면 그것이 어떤 점에서 기억에 남았는지 설명해 주세요","wordCount":16},"emotion":[],"intent":[]},"answer":{"raw":{"text":"저는 그동안 진행했던 프로젝트들 중에 가장 기억에 남는 거는 최근에 어플을 함께 개발한 적이 있었는데요 그 어플이 굉장히 성공했습니다. 어떤 어플이신지 궁금하실 텐데요. 제 이력서에 나와있는 것처럼 배달의 민족이라는 어플을 개발할 때 제가 함께 팀원으로 있었습니다. 그때 당시에 기억에 남는 거는 아이디어도 너무 좋고 시스템 체계 만드는 기술력도 다들 너무 훌륭했기 때문에 다 좋았는데 아무래도 그런 어플리케이션을 개발하고 사용자들을 모으는 것 또한 하나의 사업과 같다 보니 홍보도 필요하고 또 고객들이 불만족스러워 하는 것에 대해 파악해서 개선하고 또 개선하고 그 자리 자리에 머무르지 않고 밤낮없이 이 어플이 안정적인 자리에 오를 때까지 거의 피터지게 일을 했습니다. 그 과정이 제 기억에 정말 많이 남아있고 그 끝에 이런 큰 성공을 이루게 됐다는 점에서도 제 기억에 가장 남을 수 밖에 없다고 생각이 듭니다. 최근에 이 어플이 다른 곳으로 인수가 되면서 나오게 됐는데요. 나오게 돼서 아쉽기는 하지만 그동안 맡았던 프로젝트들 중에서 가장 훌륭한 성과를 냈고 또 가장 제가 열심을 다해서 살았던 때이기 때문에 평생 잊지 못하는 그런 프로젝트가 될 것 같습니다.","wordCount":155},"emotion":[],"intent":[{"text":"","expression":"","category":"attitude"}],"summary":{"text":"배달의 민족이라는 어플을 개발할 때 함께 팀원으로 있었는데, 아이디어와 시스템 체계 만드는 기술력 모두 훌륭했지만 홍보와 고객의 불만족스러움을 파악해서 개선하고 안정화될 때까지 피튀기며 일했던 그 과정이 제 기억에 많이 남아있습니다. 이 어플이 다른 곳으로 인수가 되면서 나오게 됐지만, 역대로 가장 훌륭한 프로젝트가 될 것 같습니다.","wordCount":45}}},"rawDataInfo":{"question":{"fileFormat":"wav","fileSize":312398,"duration":9760,"samplingBit":16,"channelCount":1,"samplingRate":"16kHz","audioPath":"/Mock/05.ICT/Female/New/ckmk_q_ict_f_n_318046.wav"},"answer":{"fileFormat":"wav","fileSize":3825358,"duration":119540,"samplingBit":16,"channelCount":1,"samplingRate":"16kHz","audioPath":"/Mock/05.ICT/Female/New/ckmk_a_ict_f_n_318046.wav"}}}