{"version":"1.0","dataSet":{"info":{"date":"20230116","occupation":"ICT","channel":"MOCK","place":"ONLINE","gender":"FEMALE","ageRange":"-34","experience":"NEW"},"question":{"raw":{"text":"배달의민족 서비스에서 좀 개선할 방안이 있다면은 말씀해 주세요","wordCount":8},"emotion":[],"intent":[]},"answer":{"raw":{"text":"저는 어 예전에 배달의민족 서비스를 자주 이용해 왔습니다. 하지만 요즘은 잘 사용하지 않습니다. 그 이유는 배달의민족의 아쉬운 부분 때문입니다. 배달의민족은 집에서도 편하게 결제를 하고 비대면으로 어 배달을 도 받을 수 있는 어 그런 좋은 서비스를 해주고 있습니다. 하지만 아쉬운 부분은 최소 주문 금액과 배달비입니다. 어 배달비가 비싸면 최소 주문 금액이 낮지만 배달비가 싸면 또 최소 주는 금액이 만 이천 원 만 오천 원 이상 넘어가면서 일 인분을 주문하기가 힘들어집니다. 배달비가 비싸고 최소 주문 금액이 너무 높아서 배달의민족 서비스를 이용할 때 항상 아쉽습니다. 그래서 어 적은 양의 나 아니면 일 인분 정도의 어 그런 각 간편한 배달을 시키고 싶어도 늘상 어 배달료를 싸게 하기 위해서 혹은 어 그래서 많이 시키게 됩니다. 그런 점이 아쉽습니다.","wordCount":113},"emotion":[],"intent":[{"text":"","expression":"","category":"attitude"}],"summary":{"text":"배달의민족은 비대면으로 배달을 받을 수 있는 좋은 서비스를 해주고 있지만, 배달비가 비싸면 최소 주문 금액이 낮지만 배달비가 싸면 또 최소 주는 금액이 만 이천 원 만 오천 원 이상 넘어가면서 일 인분을 주문하기가 힘들어집니다.","wordCount":34}}},"rawDataInfo":{"question":{"fileFormat":"wav","fileSize":249998,"duration":7810,"samplingBit":16,"channelCount":1,"samplingRate":"16kHz","audioPath":"/Mock/05.ICT/Female/New/ckmk_q_ict_f_n_50923.wav"},"answer":{"fileFormat":"wav","fileSize":2886158,"duration":90190,"samplingBit":16,"channelCount":1,"samplingRate":"16kHz","audioPath":"/Mock/05.ICT/Female/New/ckmk_a_ict_f_n_50923.wav"}}}