{"version":"1.0","dataSet":{"info":{"date":"20230116","occupation":"ICT","channel":"MOCK","place":"ONLINE","gender":"MALE","ageRange":"35-44","experience":"NEW"},"question":{"raw":{"text":"시간이 촉박한 상황에서 어떻게 시간 관리를 하시는지 궁금합니다 지원자 분의 시간 관리법을 말해주세요","wordCount":13},"emotion":[],"intent":[]},"answer":{"raw":{"text":"어 저의 가장 큰 장점 중의 하나가 그 타임 그 타임 스케줄링이라고 볼 수 있는데요. 어 지난 그 대학을 다니는 그 대학 재학 시절부터 굉장히 이런 시간 관리에 대해서 굉장히 큰 어 강점을 가지고 있다고 생각했어요. 저는 스스로 어 이제 분 단위로 많은 그 스케줄을 쪼개 쪼개면서 여러 가지 그 일정들을 하루에 다 소화해 낼 수 있었던 그런 능력이 굉장히 강한 사람이라고 저 저 스스로 많이 자부하는데요. 그래서 질문과 같이 시간이 아무리 촉박한 상황이라도 어 굉장히 철저하게 시간 관리를 하는 장점이 있습니다. 그 시간 관리를 하는 그런 어떤 어 법칙이 있다면은 그 어떤 하나 하나의 테스크마다 우선순위를 부여를 하고 있고요. 어 제가 지금 이 직무 지원을 하게 된 이 아이티 포지션에 대해서는 가장 큰 우선순위가 어 직원들의 원활한 어 아이티 오퍼레이팅이 아닐까 싶어서 어 어떤 많은 일들이 저에게 떨어져도 직원의 원활한 업무 환경을 조성하는 게 가장 큰 우선순위에 배치되어야 될 거라고 생각합니다.","wordCount":142},"emotion":[],"intent":[{"text":"","expression":"","category":"attitude"}],"summary":{"text":"저는 타임 그 타임 스케줄링에 강점이 있어서 시간이 아무리 촉박한 상황이라도 철저하게 시간 관리를 하는 장점이 있습니다. 제가 직무 지원을 하게 된 이 아이티 포지션에 대해서는 직원의 원활한 업무 환경을 조성하는 게 가장 큰 우선순위에 배치되어야 될 것이라 생각합니다.","wordCount":39}}},"rawDataInfo":{"question":{"fileFormat":"wav","fileSize":243918,"duration":7620,"samplingBit":16,"channelCount":1,"samplingRate":"16kHz","audioPath":"/Mock/05.ICT/Male/New/ckmk_q_ict_m_n_379974.wav"},"answer":{"fileFormat":"wav","fileSize":2618318,"duration":81820,"samplingBit":16,"channelCount":1,"samplingRate":"16kHz","audioPath":"/Mock/05.ICT/Male/New/ckmk_a_ict_m_n_379974.wav"}}}