{"version":"1.0","dataSet":{"info":{"date":"20230116","occupation":"ICT","channel":"MOCK","place":"ONLINE","gender":"FEMALE","ageRange":"-34","experience":"NEW"},"question":{"raw":{"text":"지원자님만의 스트레스 해소 방법이 있으신지 궁금한데요 또 그러한 방법으로 스트레스를 해소하시는 이유가 무엇인지도 말씀해 주시길 바랍니다","wordCount":16},"emotion":[],"intent":[]},"answer":{"raw":{"text":"어 저는 주로 어 내향적인 스트레스 해소법과 외향적인 스트레스 해소법이 있습니다. 첫 번째로 내향적인 스트레스 해소법은 그냥 순수하게 침대에 계속 누워 있는 것입니다. 그때 어 제가 좋아하는 눈 안마기를 사용하거나 제가 좋아하는 째즈 음악을 듣거나 어 걸그룹 음악을 듣거나 그런 취미 활동을 즐기는 집 안에서 활동을 즐기는 것이 있구요. 어 집 밖에서는 자전거를 타거나 헬스장에 가거나 아니면 친구들과 놀거나 아니면 어 어 조금의 음주를 하거나 그런 외향적인 에너지를 받으면서 어 제가 스트레스를 푸는 것도 있습니다. 그리고 어 개발자로서에 또 다른 스트레스 해소법이 있는데요. 어 개발자로서 제가 정말 막혔던 어 문제나 논리가 뭐 제가 종이에 적으면서 해결됐을 때 제가 이때까지 쌓였던 스트레스가 팡 해소된 해소되는 것이 있었습니다.","wordCount":106},"emotion":[],"intent":[{"text":"","expression":"","category":"attitude"}],"summary":{"text":"내향적 스트레스 해소법은 그냥 순수하게 침대에 계속 누워 있는 것입니다. 그리고 외향적 에너지 해소법은 자전거, 헬스장, 친구들과 놀거나 음주를 하면서 스트레스를 풀면서, 개발자로서 막혔던 문제를 종이에 적으면서 해소되는 것이 있습니다.","wordCount":30}}},"rawDataInfo":{"question":{"fileFormat":"wav","fileSize":531278,"duration":16600,"samplingBit":16,"channelCount":1,"samplingRate":"16kHz","audioPath":"/Mock/05.ICT/Female/New/ckmk_q_ict_f_n_351223.wav"},"answer":{"fileFormat":"wav","fileSize":2303438,"duration":71980,"samplingBit":16,"channelCount":1,"samplingRate":"16kHz","audioPath":"/Mock/05.ICT/Female/New/ckmk_a_ict_f_n_351223.wav"}}}