{"version":"1.0","dataSet":{"info":{"date":"20230116","occupation":"ICT","channel":"MOCK","place":"ONLINE","gender":"MALE","ageRange":"-34","experience":"NEW"},"question":{"raw":{"text":"일을 하다 보면 상사와 트러블이 발생할 수 있는데 어떻게 하시겠어요 또 상사가 혼내면 기분이 나쁘지는 않을까요","wordCount":16},"emotion":[],"intent":[]},"answer":{"raw":{"text":"일을 하다 보면 상사와 트러블이 생길 수 있는데 어떻게 할 것입니까. 또 상사가 혼내면 기분이 나쁘시지는 않을까 이렇게 질문해 주셨는데요. 일을 하다 보면 어 무조건 있을 수 있는 일이라 생각하고 저와 생각이 다 얼맞지 않는 사람이라고 생각을 하기 때문에 뭐 그런 점이 있어서 어 좀 트러블이 생길 수 있다고 생각을 합니다. 하지만 그 부분들에 있어서 좀 잘 해결해 나가고 좀 좋은 부분들이 있다고 생각을 하기 때문에 어 트러블이 생기더라도 좀 잘 해 나가려고 노력하고 뭐 내가 잘못한 부분이나 또 좀 아쉬웠던 부분들이 있어서 좀 잘 해결해 나가려고 노력을 한다면 좀 좋은 결과가 있을 거라고 생각하는데요. 그런 부분에 있어서 내 잘못인지 아니면 상사님이 좀 어 맞지 않는 답을 내가 알았던 것인지 등을 좀 잘 생각하다 보면 좋은 결과도 있을 거고 또 그런 결과들을 통해서 좀 더 어 데이터나 이런 성장할 수 있는 그런 계기가 될 것 같다 생각하기 때문에 트러블이 생겨도 일단 나의 어 내 답이 맞다고 생각하면 그 답을 좀 강조하고 어 틀린 답이라면 정중하게 사과하면서 인정하는 부분이 굉장히 좋을 것 같다고 생각하고요. 또 그렇게 잘 행하다 보면 더 좋은 결과를 만들어내기 위해서 도약할 수 있다고 생각하기 때문에 뭐 혼내면 기분이 나쁘지만 내가 잘못한 부분이나 뭐 그런 부분에 있어서는 어 좀 더 잘하고 적응을 하면서 더 좋은 결과를 만들어낼 수 있음에 좀 더 어 성장할 수 있는 계기가 된다고 생각하기 때문에 어떻게 기분이 나쁘지는 않을 거 같고 좀 더 잘 할려고 노력해야 할 거 같습니다.","wordCount":225},"emotion":[],"intent":[{"text":"","expression":"","category":"attitude"}],"summary":{"text":"일을 하다 보면 트러블이 생길 수 있지만 잘 해결해 나가려고 노력한다면 좋은 결과가 있을 것이라고 생각합니다. 저의 답이 맞다고 생각하면 그 답을 강조하고 틀린 답이라면 정중하게 사과하면서 인정하는 부분이 굉장히 좋을 것 같습니다. 그렇게 잘 행하다 보면 더 좋은 결과를 만들어내기 위해서 도약할 수 있다고 생각하기 때문에 어떻게 기분이 나쁘지는 않을 거 같고 좀 더 잘 할려고 노력해야 할 거 같습니다","wordCount":61}}},"rawDataInfo":{"question":{"fileFormat":"wav","fileSize":316238,"duration":9880,"samplingBit":16,"channelCount":1,"samplingRate":"16kHz","audioPath":"/Mock/05.ICT/Male/New/ckmk_q_ict_m_n_427214.wav"},"answer":{"fileFormat":"wav","fileSize":3632718,"duration":113520,"samplingBit":16,"channelCount":1,"samplingRate":"16kHz","audioPath":"/Mock/05.ICT/Male/New/ckmk_a_ict_m_n_427214.wav"}}}