{"version":"1.0","dataSet":{"info":{"date":"20230116","occupation":"ICT","channel":"MOCK","place":"ONLINE","gender":"MALE","ageRange":"-34","experience":"NEW"},"question":{"raw":{"text":"과거에 프로젝트를 수행해 본 경험이 있으신가요 있다면 그 프로젝트에서는 어떤 역할을 맡으셨었나요","wordCount":12},"emotion":[],"intent":[]},"answer":{"raw":{"text":"네 프로젝트를 수행했던 경험은 있습니다. 프로젝트 내에서 맡았던 역할은 주로 방향성을 제시하는 역할이었습니다. 저는 아는 것이 많이 없어서 어떻게 보면 강점이 많이 드러난다 라고는 생각하지 않습니다. 그만큼 자신감이 강한 것도 아니구요. 하지만 제가 생각하는 저의 강점은 남들이 보지 못하는 무언가를 볼 수 있다 라고 생각합니다. 그래서인지 저를 빼놓고 진행하는 것보다 저를 껴놓고 진행할 때 주로 신선하고 좋은 결과들이 많이 나왔다 라고 생각합니다. 정말 멋진 기술자들이 멋진 기술들을 만들어내면 그것들에 대해서 생명력을 부여해 주는 역할을 저는 생각하지만 될 때도 있고 안 될 때도 있습니다. 현재로써는 더 그런 역할에 맞게 하기 위해서 발전시켜 보고 싶습니다 저 스스로를. 네 더 발전시켜 봐야죠. 감사합니다.","wordCount":100},"emotion":[],"intent":[{"text":"","expression":"","category":"attitude"}],"summary":{"text":"네 프로젝트 수행경험은 있습니다. 프로젝트 내에서 맡았던 역할은 방향성을 제시하는 역할이었습니다. 제가 생각하는 저의 강점은 남들이 보지 못하는 무언가를 볼 수 있다는 것입니다. 네 네 발전시켜 봐야겠습니다.","wordCount":27}}},"rawDataInfo":{"question":{"fileFormat":"wav","fileSize":293198,"duration":9160,"samplingBit":16,"channelCount":1,"samplingRate":"16kHz","audioPath":"/Mock/05.ICT/Male/New/ckmk_q_ict_m_n_315615.wav"},"answer":{"fileFormat":"wav","fileSize":2739918,"duration":85620,"samplingBit":16,"channelCount":1,"samplingRate":"16kHz","audioPath":"/Mock/05.ICT/Male/New/ckmk_a_ict_m_n_315615.wav"}}}