{"version":"1.0","dataSet":{"info":{"date":"20230116","occupation":"ICT","channel":"MOCK","place":"ONLINE","gender":"MALE","ageRange":"-34","experience":"NEW"},"question":{"raw":{"text":"프로그램을 여러 가지 하셨다고 본인이 말씀을 하셨는데 그러면 본인이 생각하는 그런 좋은 코드란 어떤 것이라고 생각을 하시는지 왜 그것을 그렇게 생각하시는지 자세하게 말씀해 주세요","wordCount":24},"emotion":[],"intent":[]},"answer":{"raw":{"text":"좋은 코드라고 말씀하신다면 저는 많은 사람들이 보고 이해를 쉽게 할 수 있는 아주 보편적인 코드가 가장 좋은 코드라고 생각합니다. 많은 사람들이 이해를 하고 일을 발전시킬 수 있어야 개발자 개개인의 능력에 한계를 겪지 않고 더더욱 코드가 성장해 나가 개발자가 처음 의도한 것 보다도 더 높은 성과를 이룰 수 있을 것이기 때문입니다. 따라서 저도 미래에 코딩을 하게 된다면 그런 많은 사람들이 모두 이해를 할 수 있는 그런 간결하고 보편적인 코딩을 진행하고 싶습니다.","wordCount":70},"emotion":[],"intent":[{"text":"","expression":"","category":"attitude"}],"summary":{"text":"많은 사람들이 보고 이해를 쉽게 할 수 있는 보편적인 코드가 개발자가 처음 의도한 것 보다 더 높은 성과를 이룰 수 있는 가장 좋은 코드라고 생각합니다.","wordCount":25}}},"rawDataInfo":{"question":{"fileFormat":"wav","fileSize":561998,"duration":17560,"samplingBit":16,"channelCount":1,"samplingRate":"16kHz","audioPath":"/Mock/05.ICT/Male/New/ckmk_q_ict_m_n_271315.wav"},"answer":{"fileFormat":"wav","fileSize":1852878,"duration":57900,"samplingBit":16,"channelCount":1,"samplingRate":"16kHz","audioPath":"/Mock/05.ICT/Male/New/ckmk_a_ict_m_n_271315.wav"}}}