{"version":"1.0","dataSet":{"info":{"date":"20230116","occupation":"ICT","channel":"MOCK","place":"ONLINE","gender":"MALE","ageRange":"-34","experience":"NEW"},"question":{"raw":{"text":"지원한 직무와 다른 부서에 배치된다면 어떻게 하겠는가","wordCount":7},"emotion":[],"intent":[]},"answer":{"raw":{"text":"제가 지원한 부서와 다른 부서와 배치되었더라도 일단 우선 맡은 업무를 성실히 수행해 내겠습니다. 경력직과 달리 아직 업무 능력이 부족한 신입사원들은 회사에 다양한 업무를 접할 수 있는 기회라고 생각하고요. 후에 지원 부서에 배치되었을 때 다른 부서랑 연계해서 시너지 효과를 낼 수도 있다고 생각합니다.","wordCount":42},"emotion":[{"text":"제가 지원한 부서와 다른 부서와 배치되었더라도 일단 우선 맡은 업무를 성실히 수행해 내겠습니다.","expression":"p-interest","category":"positive"},{"text":"경력직과 달리 아직 업무 능력이 부족한 신입사원들은 회사에 다양한 업무를 접할 수 있는 기회라고 생각하고요.   후에 지원 부서에 배치되었을 때 다른 부서랑 연계해서 시너지 효과를 낼 수도 있다고 생각합니다.","expression":"u-belief","category":"neutral"}],"intent":[{"text":"아직 업무 능력이 부족한 신입사원들은 회사에 다양한 업무를 접할 수 있는 기회라고 생각하고요.   후에 지원 부서에 배치되었을 때 다른 부서랑 연계해서 시너지 효과를 낼 수도 있다고 생각합니다.","expression":"c_value","category":"background"}],"summary":{"text":"업무 능력이 부족한 신입사원들은 다양한 업무를 접할 수 있는 기회라고 생각하며 다른 부서와 연계해서 시너지 효과를 낼 수도 있다고 생각합니다.","wordCount":20}}},"rawDataInfo":{"question":{"fileFormat":"wav","fileSize":198478,"duration":6200,"samplingBit":16,"channelCount":1,"samplingRate":"16kHz","audioPath":"/Mock/05.ICT/Male/New/ckmk_q_ict_m_n_8199.wav"},"answer":{"fileFormat":"wav","fileSize":688078,"duration":21500,"samplingBit":16,"channelCount":1,"samplingRate":"16kHz","audioPath":"/Mock/05.ICT/Male/New/ckmk_a_ict_m_n_8199.wav"}}}