{"version":"1.0","dataSet":{"info":{"date":"20230116","occupation":"ICT","channel":"MOCK","place":"ONLINE","gender":"MALE","ageRange":"45-54","experience":"NEW"},"question":{"raw":{"text":"귀하가 여태까지 살아오시면서 가장 후회되는 것이 있다면 그것이 무엇인지 간단하게 말씀해 주세요","wordCount":12},"emotion":[],"intent":[]},"answer":{"raw":{"text":"인생에서 가장 후회되는 것이 있다면 제 개인적인 개인적인 부분은 제가 인문계 고등학교를 나와서 대학교에 실패를 하고 재수 삼수를 하며 그 보냈던 시간들 그리고 결론적으로는 그 재수 삼수를 하면서 대학 수석으로 들어가긴 했지만 그 대학교를 일 년 밖에 다니지 않고 끝내는 졸업하지 못하고 중퇴를 하고 중국에 대학을 졸업한 부분이 제 인생에서 가장 후회되는 부분입니다. 그 당시에는 인문계 고등학생이 대학을 들어가지 못했다고 하면 인생에서 실패를 했다고 생각하는 사회적 분위기가 있었습니다. 지금 생각해 보면 인생은 마라톤과 같이 길고 본인이 어떻게 설계를 하고 준비를 하며 진행해 오는 거에 따라서는 얼마든지 바뀔 수 있다는 생각을 하고 있지만 그 당시에는 그러한 부분이나 그리고 어 여러 가지 정보나 그 집안 사정 또한 그런 부분들을 에 제 다른 부분들 제시할 수 있는 부분이 안 되었기 때문에 저의 반대로 지금 저 아이들이 재수나 삼수를 한다 그러면 적극 말리고 싶습니다.","wordCount":130},"emotion":[],"intent":[{"text":"","expression":"","category":"attitude"}],"summary":{"text":"저는 인문계 고등학교를 나와서 대학교를 일 년 밖에 다니지 않고 중퇴하고 중국에 대학을 졸업한 부분이 가장 후회되는 부분입니다. 그 당시에 인문계 고등학생이 대학을 들어가지 못했다면 인생에서 실패를 했다고 생각하는 사회적 분위기가 있었는데 아이들이 재수나 삼수를 한다 그러면 적극 말리고 싶습니다.","wordCount":40}}},"rawDataInfo":{"question":{"fileFormat":"wav","fileSize":379278,"duration":11850,"samplingBit":16,"channelCount":1,"samplingRate":"16kHz","audioPath":"/Mock/05.ICT/Male/New/ckmk_q_ict_m_n_51516.wav"},"answer":{"fileFormat":"wav","fileSize":2730958,"duration":85340,"samplingBit":16,"channelCount":1,"samplingRate":"16kHz","audioPath":"/Mock/05.ICT/Male/New/ckmk_a_ict_m_n_51516.wav"}}}