{"version":"1.0","dataSet":{"info":{"date":"20230116","occupation":"ICT","channel":"MOCK","place":"ONLINE","gender":"FEMALE","ageRange":"55-","experience":"NEW"},"question":{"raw":{"text":"직무를 수행하다 보면 어 내가 모르는 문제가 나올 수도 있는데 어 모르는 그런 과제에 대해서 지원자님께서 해결하는 방법이 궁금합니다","wordCount":19},"emotion":[],"intent":[]},"answer":{"raw":{"text":"직무 수행 시 모르는 과제에 대해서 해결하는 방법은 어 그렇게 질문을 해 주셨는데요. 어 직무 수행 시 모르는 과제 어 그거를 해결하는 방법이라. 어 일단은 모르는 게 있으면 어 유튜브라든가 네이버라든가를 통해서 어 어 그 검색을 해서 먼저 어 질 그까 모르는 거를 알아야 되겠고 어 그리고 그거를 알았으면 또 나 혼자만 알고 있으면 안 될 것 같고 같이 동료들과 어 같이 공유하고 어 같이 어 공부하고 같이 배우면서 어 그렇게 배우면서 어 그 직무를 잘 수행할 것 같습니다. 그래서 어 동료들한테도 인정받고 어 그런 나 그런 동료가 되고 싶습니다. 그러기 위해서는 더 많이 노력해야 되고 더 많이 어 공부를 해야 된다 라고 생각을 합니다. 그렇게 할 것입니다. 이상입니다. 감사합니다.","wordCount":110},"emotion":[{"text":"감사합니다.","expression":"p-gratitude","category":"positive"}],"intent":[{"text":"","expression":"","category":"attitude"}],"summary":{"text":"직무 수행 시 모르는 것을 해결하는 방법은 유튜브나 네이버 등에서 검색해서 모르는 것을 알고 공유하며 함께 배우며 직무를 잘 수행할 수 있을 것 같습니다. 인정받는 동료가 되고 싶으며 더 많이 공부하고 공부해야 될 것입니다.","wordCount":34}}},"rawDataInfo":{"question":{"fileFormat":"wav","fileSize":514638,"duration":16079,"samplingBit":16,"channelCount":1,"samplingRate":"16kHz","audioPath":"/Mock/05.ICT/Female/New/ckmk_q_ict_f_n_15368.wav"},"answer":{"fileFormat":"wav","fileSize":2813838,"duration":87930,"samplingBit":16,"channelCount":1,"samplingRate":"16kHz","audioPath":"/Mock/05.ICT/Female/New/ckmk_a_ict_f_n_15368.wav"}}}