{"version":"1.0","dataSet":{"info":{"date":"20230116","occupation":"ICT","channel":"MOCK","place":"ONLINE","gender":"MALE","ageRange":"55-","experience":"NEW"},"question":{"raw":{"text":"그동안 속해 있었던 조직들 속에서 지원자님은 주로 어떤 일을 하는 사람이었습니까","wordCount":11},"emotion":[],"intent":[]},"answer":{"raw":{"text":"저는 이전에 인제 목수 때 빌더로서 경력이 뭐 한 이십 년 가까이 되니까 어 처음에야 이제 빌더로 작은 빌더로 시작을 했지만 어 뭐 한 삼 년 아 오 년 뭐 이렇게 되면서 인제 에 팀을 꾸려 가지고 어 팀장을 하면서 또 인제 그 영업도 하게 되고 어 그렇게 됐는데 사실은 그런 과정이 있었지만 일거리를 제가 많이 영업을 못 해 가지고 결국에 인제 팀을 또 해체하기도 하고 어 또 어 회사에 하도급 현장 소장도 해 보면서 어 쓴맛도 봤고 음 이런 이제 그 일련의 과정을 쭉 거치면서 어 뭐 최근에는 어 산청에 있는 뭐 인제 그 목조 주택 회사에 어 어 팀장으로서 이 역할을 했습니다. 제가 팀을 꾸려 가지고 어 그 회사가 계약한 건축주의 주택을 어 저희들이 인제 골조부터 해서 마감까지 요렇게 인제 어 마무리하는 완축을 하는 그런 이제 공사를 했고 어 집을 짓기 위해서는 많은 공정들이 들어가죠. 이제 외장 그리고 뭐 지붕 그리고 뭐 인제 설비 뭐 전기 어 조명 뭐 이런 게 들어가는데 그러다 보면은 또 이제 현장 소장 역할도 어 겸해야 됩니다. 뭐 건축주와의 관계도 어 상당히 원만해야 되고 그리고 어 건축주와의 커뮤니케이션도 좋아야 어 또 어 좋은 어 평을 또 이끌어 낼 수가 있고 그런 역할을 했습니다.","wordCount":190},"emotion":[],"intent":[{"text":"","expression":"","category":"attitude"}],"summary":{"text":"저는 목수 때 빌더로서 경력이 20년 가까이 되었지만 팀을 꾸려서 팀장을 하면서 영업을 많이 못해 결국은 팀을 해체하고 회사에 하도급 현장 소장도 해 보면서 쓴맛도 보고 최근에는 산청에 있는 목조 주택 회사에 팀장으로서 역할을 했습니다. 집을 짓기 위해서는 많은 공정들이 들어가는데 현장 소장 역할도 겸해야 되고 건축주와의 관계도 원만해야 될 것 같습니다.","wordCount":52}}},"rawDataInfo":{"question":{"fileFormat":"wav","fileSize":257998,"duration":8060,"samplingBit":16,"channelCount":1,"samplingRate":"16kHz","audioPath":"/Mock/05.ICT/Male/New/ckmk_q_ict_m_n_426525.wav"},"answer":{"fileFormat":"wav","fileSize":3667278,"duration":114600,"samplingBit":16,"channelCount":1,"samplingRate":"16kHz","audioPath":"/Mock/05.ICT/Male/New/ckmk_a_ict_m_n_426525.wav"}}}